Workbook

Sheet Підсумок
A1: Звірка цін каталогу Majstr з ринком — 25.10.2026
A2: Ціни — тільки робота, ₴. Ринок — відкриті прайси майстрів і компаній та маркетплейси (Київ, Львів, Україна), переважно 2026 р.
A4: Група | B4: Перевірено | C4: В ринку | D4: Підняти | E4: Знизити | F4: Неясно | G4: Аномалій
A5: Плитка і підлоги | B5: =COUNTIFS(Звірка!$A$2:$A$309,A5) -> 68 | C5: =COUNTIFS(Звірка!$A$2:$A$309,$A5,Звірка!$I$2:$I$309,"в ринку") -> 39 | D5: =COUNTIFS(Звірка!$A$2:$A$309,$A5,Звірка!$I$2:$I$309,"підняти") -> 22 | E5: =COUNTIFS(Звірка!$A$2:$A$309,$A5,Звірка!$I$2:$I$309,"знизити") -> 5 | F5: =COUNTIFS(Звірка!$A$2:$A$309,$A5,Звірка!$I$2:$I$309,"неясно") -> 2 | G5: =COUNTIFS(Аномалії!$A$2:$A$131,A5) -> 32
A6: Малярка і гіпсокартон | B6: =COUNTIFS(Звірка!$A$2:$A$309,A6) -> 50 | C6: =COUNTIFS(Звірка!$A$2:$A$309,$A6,Звірка!$I$2:$I$309,"в ринку") -> 29 | D6: =COUNTIFS(Звірка!$A$2:$A$309,$A6,Звірка!$I$2:$I$309,"підняти") -> 14 | E6: =COUNTIFS(Звірка!$A$2:$A$309,$A6,Звірка!$I$2:$I$309,"знизити") -> 6 | F6: =COUNTIFS(Звірка!$A$2:$A$309,$A6,Звірка!$I$2:$I$309,"неясно") -> 1 | G6: =COUNTIFS(Аномалії!$A$2:$A$131,A6) -> 23
A7: Електрика | B7: =COUNTIFS(Звірка!$A$2:$A$309,A7) -> 60 | C7: =COUNTIFS(Звірка!$A$2:$A$309,$A7,Звірка!$I$2:$I$309,"в ринку") -> 27 | D7: =COUNTIFS(Звірка!$A$2:$A$309,$A7,Звірка!$I$2:$I$309,"підняти") -> 13 | E7: =COUNTIFS(Звірка!$A$2:$A$309,$A7,Звірка!$I$2:$I$309,"знизити") -> 17 | F7: =COUNTIFS(Звірка!$A$2:$A$309,$A7,Звірка!$I$2:$I$309,"неясно") -> 3 | G7: =COUNTIFS(Аномалії!$A$2:$A$131,A7) -> 16
A8: Сантехніка | B8: =COUNTIFS(Звірка!$A$2:$A$309,A8) -> 69 | C8: =COUNTIFS(Звірка!$A$2:$A$309,$A8,Звірка!$I$2:$I$309,"в ринку") -> 27 | D8: =COUNTIFS(Звірка!$A$2:$A$309,$A8,Звірка!$I$2:$I$309,"підняти") -> 34 | E8: =COUNTIFS(Звірка!$A$2:$A$309,$A8,Звірка!$I$2:$I$309,"знизити") -> 7 | F8: =COUNTIFS(Звірка!$A$2:$A$309,$A8,Звірка!$I$2:$I$309,"неясно") -> 1 | G8: =COUNTIFS(Аномалії!$A$2:$A$131,A8) -> 24
A9: Будівельник, демонтаж, метал | B9: =COUNTIFS(Звірка!$A$2:$A$309,A9) -> 61 | C9: =COUNTIFS(Звірка!$A$2:$A$309,$A9,Звірка!$I$2:$I$309,"в ринку") -> 21 | D9: =COUNTIFS(Звірка!$A$2:$A$309,$A9,Звірка!$I$2:$I$309,"підняти") -> 32 | E9: =COUNTIFS(Звірка!$A$2:$A$309,$A9,Звірка!$I$2:$I$309,"знизити") -> 5 | F9: =COUNTIFS(Звірка!$A$2:$A$309,$A9,Звірка!$I$2:$I$309,"неясно") -> 3 | G9: =COUNTIFS(Аномалії!$A$2:$A$131,A9) -> 35
A10: Разом | B10: =SUM(B5:B9) -> 308 | C10: =SUM(C5:C9) -> 143 | D10: =SUM(D5:D9) -> 115 | E10: =SUM(E5:E9) -> 40 | F10: =SUM(F5:F9) -> 10 | G10: =SUM(G5:G9) -> 130
A11: Нових позицій запропоновано | B11: =COUNTA('Нові позиції'!$C$2:$C$64) -> 63
A12: Рішень уже прийнято (Звірка) | B12: =COUNTA(Звірка!$L$2:$L$309) -> 0
A14: Як користуватись:
A15: • «Звірка»: у жовтій колонці «Рішення» обери Прийняти / Відхилити / Своя ціна (тоді впиши її поруч). «Підсумкова ціна» порахується сама — цей стовпчик і піде в міграцію.
A16: • «Аномалії»: помилки одиниць, дублікати з різними цінами, нулі, «заглушки» (однакова ціна на різні роботи).
A17: • «Нові позиції»: що часто є в прайсах майстрів, а в нас немає. Постав «Так» і ціну — додамо.
A18: • Порожні жовті клітинки = рішення ще не прийняте; така позиція лишається за нашою ціною.
A19: Важливо: stroyremdizayn.kiev.ua і demontazh-pro.kiev.ua збігаються з нашим каталогом майже 1:1 — схоже, звідти колись брали ціни. Аудитори не рахували їх незалежними джерелами.
A20: Чужі бази цін кошторисних застосунків (напр. lihtar.app) не використовувались.

Sheet Звірка
A1: Група | B1: Фах | C1: Позиція | D1: Од. | E1: Наша ціна, ₴ | F1: Ринок мін, ₴ | G1: Ринок медіана, ₴ | H1: Ринок макс, ₴ | I1: Вердикт | J1: Пропонована ціна, ₴ | K1: Зміна, % | L1: Рішення | M1: Своя ціна, ₴ | N1: Підсумкова ціна, ₴ | O1: Примітка аудитора | P1: Джерела (URL · що написано · місто · дата)
A2: Плитка і підлоги | B2: Підлоги | C2: Демонтаж лінолеуму ковроліну | D2: м² | E2: 20 | F2: 80 | G2: 130 | H2: 250 | I2: підняти | J2: 100 | K2: =IF(AND(ISNUMBER(J2),E2>0),J2/E2-1,"") -> 4 | N2: =IF(L2="Своя ціна",M2,IF(L2="Прийняти",IF(ISNUMBER(J2),J2,E2),E2)) -> 20 | O2: 20 грн/м² явно замало. Медіана 130; пропоновано 100 (лінолеум без клею). | P2: https://rbk-alba.com/ua/price · лінолеум 250 / на клей 300 · не вказано · 19.10.2026 https://kabanchik.ua/ua/kyiv/category/ukladannia-laminatu · демонтаж старого покриття 130 · Київ · 10.2026 https://rating-remont-kvartir.com.ua/ua/rozcinki-na-roboti-z-pidlogami-lviv/ · демонтаж покриття 60–100 · Львів · 07.01.2026
A3: Плитка і підлоги | B3: Підлоги | C3: Машинна стяжка самовирівнююча | D3: м² | E3: 301 | F3: 350 | G3: 362 | H3: 373 | I3: підняти | J3: 350 | K3: =IF(AND(ISNUMBER(J3),E3>0),J3/E3-1,"") -> 0.1627907 | N3: =IF(L3="Своя ціна",M3,IF(L3="Прийняти",IF(ISNUMBER(J3),J3,E3),E3)) -> 301 | O3: Наша ціна нижча навіть за мінімум rabotniki (307). | P3: https://www.rabotniki.ua/uk/chernovye-raboty-po-polu/kiev · машинна самовирівнююча 307/373/400 грн/м² · Київ · 2026 https://mirafloor.com.ua/statti/nalivna-pidloga-tsina-za-m2.html · наливна від 350 · Київ · 09.2026
A4: Плитка і підлоги | B4: Підлоги | C4: Монтаж алюмінієвого плінтуса | D4: м.п. | E4: 312 | F4: 350 | G4: 375 | H4: 400 | I4: підняти | J4: 370 | K4: =IF(AND(ISNUMBER(J4),E4>0),J4/E4-1,"") -> 0.18589744 | N4: =IF(L4="Своя ціна",M4,IF(L4="Прийняти",IF(ISNUMBER(J4),J4,E4),E4)) -> 312 | P4: https://stroyremdizayn.kiev.ua/rascenki-na-otdelochnye-raboty.html · алюмінієвий 400 · Київ · 2026 https://bud.arsel.com.ua/tsiny-na-budivelni-roboty/ · алюмінієвий 350 · Київ і обл. · 01.01.2026
A5: Плитка і підлоги | B5: Підлоги | C5: Настил лінолеуму ковроліну на клей | D5: м² | E5: 200 | F5: 220 | G5: 260 | H5: 300 | I5: підняти | J5: 260 | K5: =IF(AND(ISNUMBER(J5),E5>0),J5/E5-1,"") -> 0.3 | N5: =IF(L5="Своя ціна",M5,IF(L5="Прийняти",IF(ISNUMBER(J5),J5,E5),E5)) -> 200 | O5: Зараз дорівнює варіанту без клею (200), хоча на клей має бути дорожче. | P5: https://stroyremdizayn.kiev.ua/rascenki-na-otdelochnye-raboty.html · на клей 300 · Київ · 2026 https://bud.arsel.com.ua/tsiny-na-budivelni-roboty/ · лінолеум на клей 220 · Київ і обл. · 01.01.2026
A6: Плитка і підлоги | B6: Підлоги | C6: Настилання підлоги з дошки по лагах | D6: м² | E6: 400 | F6: 441 | G6: 452 | H6: 460 | I6: підняти | J6: 450 | K6: =IF(AND(ISNUMBER(J6),E6>0),J6/E6-1,"") -> 0.125 | N6: =IF(L6="Своя ціна",M6,IF(L6="Прийняти",IF(ISNUMBER(J6),J6,E6),E6)) -> 400 | P6: https://www.rabotniki.ua/uk/price/ukladka-laminata-price/kiev · дерев'яна підлога у шпунт 441 · Київ · 25.10.2026 https://www.rabotniki.ua/uk/price/tsiklevanie-parketa-pokrytie-lakom · 452 · Україна (агрегат) · 25.10.2026 https://stroyremdizayn.kiev.ua/rascenki-na-otdelochnye-raboty.html · підлога з дошки 460 · Київ · 2026
A7: Плитка і підлоги | B7: Підлоги | C7: Укладання паркетної / інженерної дошки плаваючим способом | D7: м² | E7: 420 | F7: 435 | G7: 485 | H7: 491 | I7: підняти | J7: 480 | K7: =IF(AND(ISNUMBER(J7),E7>0),J7/E7-1,"") -> 0.14285714 | N7: =IF(L7="Своя ціна",M7,IF(L7="Прийняти",IF(ISNUMBER(J7),J7,E7),E7)) -> 420 | O7: Наша ціна нижча за всі три джерела. | P7: https://www.rabotniki.ua/uk/price/ukladka-laminata-price/kiev · Київ, тришарова 491 · Київ · 25.10.2026 https://www.rabotniki.ua/uk/price/tsiklevanie-parketa-pokrytie-lakom · тришарова (Україна) 485 · Україна (агрегат) · 25.10.2026 https://bud.arsel.com.ua/tsiny-na-budivelni-roboty/ · тришарова 435 · Київ і обл. · 01.01.2026
A8: Плитка і підлоги | B8: Плитка | C8: Виріз отворів до 70 мм | D8: шт | E8: 196 | F8: 150 | G8: 240 | H8: 300 | I8: підняти | J8: 240 | K8: =IF(AND(ISNUMBER(J8),E8>0),J8/E8-1,"") -> 0.2244898 | N8: =IF(L8="Своя ціна",M8,IF(L8="Прийняти",IF(ISNUMBER(J8),J8,E8),E8)) -> 196 | P8: https://www.rabotniki.ua/uk/plitochnye-raboty · 150/273/400 грн/шт · Україна (агрегат) · 2026 https://www.rabotniki.ua/uk/price/ukladka-plitki-na-pol/kiev · сер. 295 · Київ · 25.10.2026 https://kabanchik.ua/ua/kyiv/category/ukladannia-plytky · 240 · Київ · 10.2026 https://plitochnik.kiev.ua/ua/%D0%B2%D0%B0%D1%80%D1%82%D1%96%D1%81%D1%82%D1%8C-%D1%80%D0%BE%D0%B1%D1%96%D1%82-%D0%BF%D0%BB%D0%B8%D1%82%D0%BE%D1%87%D0%BD%D0%B8%D0%BA%D0%B0.html · до 70 мм 204 · Київ · 2026 https://bud.arsel.com.ua/tsiny-na-budivelni-roboty/ · 220 · Київ і обл. · 01.01.2026 https://liv-comfort.kyiv.ua/price-remont/index.html · 250 · Київ · 2026 https://stroyremdizayn.kiev.ua/rascenki-na-otdelochnye-raboty.html · 300 · Київ · 2026 https://remmo.lviv.ua/plytochni-roboty-lviv/ · 200 · Львів · 25.01.2026 https://plitka.ua/ua/services/ukladannya-plitki/ · до 70 мм 150 (2025) · Київ · 2025 https://24tv.ua/skilki-naspravdi-koshtuye-poklasti-plitku-vanniy-realni-tsini_n3111316 · 250 · не вказано · 24.07.2026 https://www.remonthub.org/prices.php · 220 · Київ · 2026
A9: Плитка і підлоги | B9: Плитка | C9: Запил плитки під 45° | D9: м.п. | E9: 367 | F9: 300 | G9: 463 | H9: 550 | I9: підняти | J9: 460 | K9: =IF(AND(ISNUMBER(J9),E9>0),J9/E9-1,"") -> 0.25340599 | N9: =IF(L9="Своя ціна",M9,IF(L9="Прийняти",IF(ISNUMBER(J9),J9,E9),E9)) -> 367 | P9: https://www.rabotniki.ua/uk/plitochnye-raboty · 250/478/750 грн/м.п. · Україна (агрегат) · 2026 https://www.rabotniki.ua/uk/price/ukladka-plitki-na-pol/kiev · сер. 484 · Київ · 25.10.2026 https://www.rabotniki.ua/uk/plitochnye-raboty/lvov · 250/463/700 · Львів · 2026 https://budver.com/masters/zapil-ta-shlifuvannya-kromok-plitki-pid-45-gradusiv · 275/550/825 · Україна (агрегат) · 2026 https://kabanchik.ua/ua/kyiv/category/ukladannia-plytky · 420 · Київ · 10.2026 https://plitochnik.kiev.ua/ua/%D0%B2%D0%B0%D1%80%D1%82%D1%96%D1%81%D1%82%D1%8C-%D1%80%D0%BE%D0%B1%D1%96%D1%82-%D0%BF%D0%BB%D0%B8%D1%82%D0%BE%D1%87%D0%BD%D0%B8%D0%BA%D0%B0.html · 420 · Київ · 2026 https://bud.arsel.com.ua/tsiny-na-budivelni-roboty/ · 425 · Київ і обл. · 01.01.2026 https://liv-comfort.kyiv.ua/price-remont/index.html · 500 · Київ · 2026 https://stroyremdizayn.kiev.ua/rascenki-na-otdelochnye-raboty.html · 500 · Київ · 2026 https://remmo.lviv.ua/plytochni-roboty-lviv/ · 300 · Львів · 25.01.2026 https://plitka.ua/ua/services/ukladannya-plitki/ · 300 (2025) · Київ · 2025
A10: Плитка і підлоги | B10: Плитка | C10: Заповнення швів герметиком | D10: м.п. | E10: 130 | F10: 100 | G10: 228 | H10: 250 | I10: підняти | J10: 220 | K10: =IF(AND(ISNUMBER(J10),E10>0),J10/E10-1,"") -> 0.69230769 | N10: =IF(L10="Своя ціна",M10,IF(L10="Прийняти",IF(ISNUMBER(J10),J10,E10),E10)) -> 130 | O10: Після підвищення 'Заміна силіконового шва' (180) треба тримати вище за просте заповнення, ~280. | P10: https://www.rabotniki.ua/uk/plitochnye-raboty · герметична 150/215/350 грн/м.п. · Україна (агрегат) · 2026 https://plitochnik.kiev.ua/ua/%D0%B2%D0%B0%D1%80%D1%82%D1%96%D1%81%D1%82%D1%8C-%D1%80%D0%BE%D0%B1%D1%96%D1%82-%D0%BF%D0%BB%D0%B8%D1%82%D0%BE%D1%87%D0%BD%D0%B8%D0%BA%D0%B0.html · герметизація шва 240 грн/м.п. · Київ · 2026 https://kabanchik.ua/ua/kyiv/category/ukladannia-plytky · герметизація швів від 110 · Київ · 10.2026 https://stroyremdizayn.kiev.ua/rascenki-na-otdelochnye-raboty.html · герметик 250 грн/м.п. · Київ · 2026 https://plitka.ua/ua/services/ukladannya-plitki/ · герметик у шви 100 грн/м.п. (2025) · Київ · 2025 https://24tv.ua/skilki-naspravdi-koshtuye-poklasti-plitku-vanniy-realni-tsini_n3111316 · силікон у кутах 250 грн/м.п. · не вказано · 24.07.2026
A11: Плитка і підлоги | B11: Плитка | C11: Заповнення швів епоксидною сумішшю | D11: м² | E11: 241 | F11: 200 | G11: 290 | H11: 369 | I11: підняти | J11: 290 | K11: =IF(AND(ISNUMBER(J11),E11>0),J11/E11-1,"") -> 0.2033195 | N11: =IF(L11="Своя ціна",M11,IF(L11="Прийняти",IF(ISNUMBER(J11),J11,E11),E11)) -> 241 | O11: rabotniki (315) і arsel (320) вказують у грн/м.п. — розбіжність одиниць, не враховано. | P11: https://budver.com/masters/zatirannya-shviv-plitki-epoksidnoyu-zatirkoyu · 187/369/550 грн/м² · Україна (агрегат) · 2026 https://plitochnik.kiev.ua/ua/%D0%B2%D0%B0%D1%80%D1%82%D1%96%D1%81%D1%82%D1%8C-%D1%80%D0%BE%D0%B1%D1%96%D1%82-%D0%BF%D0%BB%D0%B8%D1%82%D0%BE%D1%87%D0%BD%D0%B8%D0%BA%D0%B0.html · 300 грн/м² · Київ · 2026 https://plitochnik.kiev.ua/ua/%D1%83%D0%BA%D0%BB%D0%B0%D0%B4%D0%B0%D0%BD%D0%BD%D1%8F-%D1%84%D0%BE%D1%80%D0%BC%D0%B0%D1%82%D0%BD%D0%BE%D0%B3%D0%BE-%D0%BA%D0%B5%D1%80%D0%B0%D0%BC%D0%BE%D0%B3%D1%80%D0%B0%D0%BD%D1%96%D1%82%D0%B0.html · 240 грн/м² · Київ · 2026 https://24tv.ua/skilki-naspravdi-koshtuye-poklasti-plitku-vanniy-realni-tsini_n3111316 · 320 грн/м² · не вказано · 24.07.2026 https://www.remonthub.org/prices.php · 290 грн/м² · Київ · 2026 https://plitka.ua/ua/services/ukladannya-plitki/ · 200 грн/м² (2025) · Київ · 2025 https://liv-comfort.kyiv.ua/price-remont/index.html · двокомпонентна 250 · Київ · 2026
A12: Плитка і підлоги | B12: Плитка | C12: Заповнення швів цементною сумішшю | D12: м² | E12: 116 | F12: 50 | G12: 173 | H12: 200 | I12: підняти | J12: 170 | K12: =IF(AND(ISNUMBER(J12),E12>0),J12/E12-1,"") -> 0.46551724 | N12: =IF(L12="Своя ціна",M12,IF(L12="Прийняти",IF(ISNUMBER(J12),J12,E12),E12)) -> 116 | O12: SR вказує 50 грн/м.п. — інша одиниця, не враховано. | P12: https://www.rabotniki.ua/uk/plitochnye-raboty · стандартна 100/166/250 грн/м² · Україна (агрегат) · 2026 https://www.rabotniki.ua/uk/price/ukladka-plitki-na-pol/kiev · сер. 182 · Київ · 25.10.2026 https://www.rabotniki.ua/uk/plitochnye-raboty/lvov · 140/163/200 · Львів · 2026 https://budver.com/masters/zatirannya-shviv-plitki · 110/193/275 · Україна (агрегат) · 2026 https://kabanchik.ua/ua/kyiv/category/ukladannia-plytky · 140 грн/м² · Київ · 10.2026 https://plitochnik.kiev.ua/ua/%D0%B2%D0%B0%D1%80%D1%82%D1%96%D1%81%D1%82%D1%8C-%D1%80%D0%BE%D0%B1%D1%96%D1%82-%D0%BF%D0%BB%D0%B8%D1%82%D0%BE%D1%87%D0%BD%D0%B8%D0%BA%D0%B0.html · до 5 мм 180 грн/м² · Київ · 2026 https://bud.arsel.com.ua/tsiny-na-budivelni-roboty/ · 120 грн/м² · Київ і обл. · 01.01.2026 https://www.remonthub.org/prices.php · 200 грн/м² · Київ · 2026 https://24tv.ua/skilki-naspravdi-koshtuye-poklasti-plitku-vanniy-realni-tsini_n3111316 · 200 грн/м² · не вказано · 24.07.2026 https://remmo.lviv.ua/plytochni-roboty-lviv/ · 50 грн/м² · Львів · 25.01.2026
A13: Плитка і підлоги | B13: Плитка | C13: Стяжка маякова цементна | D13: м² | E13: 342 | F13: 350 | G13: 400 | H13: 500 | I13: підняти | J13: 400 | K13: =IF(AND(ISNUMBER(J13),E13>0),J13/E13-1,"") -> 0.16959064 | N13: =IF(L13="Своя ціна",M13,IF(L13="Прийняти",IF(ISNUMBER(J13),J13,E13),E13)) -> 342 | O13: Дубль FLOORING 'Цементно-піщана стяжка понад 20м2' = 400. Варто вирівняти. | P13: https://www.rabotniki.ua/uk/chernovye-raboty-po-polu/kiev · ЦПС до 5 см 250/396/600 грн/м² · Київ · 2026 https://bud.arsel.com.ua/tsiny-na-budivelni-roboty/ · до 5 см 350 · Київ і обл. · 01.01.2026 https://rbk-alba.com/ua/price · до 5 см 450 · не вказано · 19.10.2026 https://plitochnik.kiev.ua/ua/%D0%B2%D0%B0%D1%80%D1%82%D1%96%D1%81%D1%82%D1%8C-%D1%80%D0%BE%D0%B1%D1%96%D1%82-%D0%BF%D0%BB%D0%B8%D1%82%D0%BE%D1%87%D0%BD%D0%B8%D0%BA%D0%B0.html · до 50 мм 480 · Київ · 2026 https://liv-comfort.kyiv.ua/price-remont/index.html · до 50 мм 400 · Київ · 2026 https://stroyremdizayn.kiev.ua/rascenki-na-otdelochnye-raboty.html · понад 20 м² 360 · Київ · 2026 https://www.remonthub.org/prices.php · до 5 см 500 · Київ · 2026
A14: Плитка і підлоги | B14: Плитка | C14: Укладання декоративної плитки під «цеглу» або «камінь» (гіпсова, бетонна) | D14: м² | E14: 0 | F14: 660 | G14: 1022 | H14: 1105 | I14: підняти | J14: 1000 | K14: =IF(AND(ISNUMBER(J14),E14>0),J14/E14-1,"") | N14: =IF(L14="Своя ціна",M14,IF(L14="Прийняти",IF(ISNUMBER(J14),J14,E14),E14)) -> 0 | O14: Ціна 0 — пропущене значення. | P14: https://www.rabotniki.ua/uk/plitochnye-raboty · декоративна гіпсова плитка 600/1105/1650 грн/м² · Україна (агрегат) · 2026 https://www.rabotniki.ua/uk/plitochnye-raboty · гіпсова цеглинка 600/1022/1500 · Україна (агрегат) · 2026 https://kabanchik.ua/ua/kyiv/category/ukladannia-plytky · декоративна гіпсова плитка 1060 грн/м² · Київ · 10.2026 https://budver.com/masters/plitochni-roboti · гіпсова плитка від 660 · Україна (ціни 'від') · 2026 https://stroyremdizayn.kiev.ua/rascenki-na-otdelochnye-raboty.html · декоративна цегла/камінь 1000 · Київ · 2026
A15: Плитка і підлоги | B15: Плитка | C15: Укладання керамічного паркету, дрібної дошки | D15: м² | E15: 866 | F15: 800 | G15: 1012 | H15: 1267 | I15: підняти | J15: 1000 | K15: =IF(AND(ISNUMBER(J15),E15>0),J15/E15-1,"") -> 0.15473441 | N15: =IF(L15="Своя ціна",M15,IF(L15="Прийняти",IF(ISNUMBER(J15),J15,E15),E15)) -> 866 | P15: https://plitochnik.kiev.ua/ua/%D0%B2%D0%B0%D1%80%D1%82%D1%96%D1%81%D1%82%D1%8C-%D1%80%D0%BE%D0%B1%D1%96%D1%82-%D0%BF%D0%BB%D0%B8%D1%82%D0%BE%D1%87%D0%BD%D0%B8%D0%BA%D0%B0.html · дрібний керамічний паркет 1200 грн/м² · Київ · 2026 https://plitka.ua/ua/services/ukladannya-plitki/ · керамопаркет 800 грн/м² (2025) · Київ · 2025 https://www.rabotniki.ua/uk/plitochnye-raboty · керамічний паркет до 1200 мм 750/1267/1810 грн/м² · Україна (агрегат) · 2026 https://budver.com/masters/plitochni-roboti · керамічний паркет від 825 грн/м² · Україна (ціни 'від') · 2026
A16: Плитка і підлоги | B16: Плитка | C16: Укладання клінкерної підлогової плитки | D16: м² | E16: 891 | F16: 770 | G16: 1080 | H16: 1244 | I16: підняти | J16: 1100 | K16: =IF(AND(ISNUMBER(J16),E16>0),J16/E16-1,"") -> 0.2345679 | N16: =IF(L16="Своя ціна",M16,IF(L16="Прийняти",IF(ISNUMBER(J16),J16,E16),E16)) -> 891 | O16: Позиція в категорії 'Облицювання сходів'. | P16: https://www.rabotniki.ua/uk/plitochnye-raboty · клінкер 700/1244/2000 грн/м² · Україна (агрегат) · 2026 https://budver.com/masters/plitochni-roboti · клінкер від 770 · Україна (ціни 'від') · 2026 https://plitochnik.kiev.ua/ua/%D0%B2%D0%B0%D1%80%D1%82%D1%96%D1%81%D1%82%D1%8C-%D1%80%D0%BE%D0%B1%D1%96%D1%82-%D0%BF%D0%BB%D0%B8%D1%82%D0%BE%D1%87%D0%BD%D0%B8%D0%BA%D0%B0.html · промисловий клінкер 1080 · Київ · 2026 https://stroyremdizayn.kiev.ua/rascenki-na-otdelochnye-raboty.html · клінкер 1200 · Київ · 2026 https://remmo.lviv.ua/plytochni-roboty-lviv/ · клінкер від 1000 · Львів · 25.01.2026
A17: Плитка і підлоги | B17: Плитка | C17: Укладання плитки 1200х1200 мм | D17: м² | E17: 1130 | F17: 1250 | G17: 1345 | H17: 1440 | I17: підняти | J17: 1300 | K17: =IF(AND(ISNUMBER(J17),E17>0),J17/E17-1,"") -> 0.15044248 | N17: =IF(L17="Своя ціна",M17,IF(L17="Прийняти",IF(ISNUMBER(J17),J17,E17),E17)) -> 1130 | P17: https://plitochnik.kiev.ua/ua/%D1%83%D0%BA%D0%BB%D0%B0%D0%B4%D0%B0%D0%BD%D0%BD%D1%8F-%D1%84%D0%BE%D1%80%D0%BC%D0%B0%D1%82%D0%BD%D0%BE%D0%B3%D0%BE-%D0%BA%D0%B5%D1%80%D0%B0%D0%BC%D0%BE%D0%B3%D1%80%D0%B0%D0%BD%D1%96%D1%82%D0%B0.html · 1200×1200 1440 грн/м² · Київ · 2026 https://stroyremdizayn.kiev.ua/rascenki-na-otdelochnye-raboty.html · 1200×1200 1250 грн/м² · Київ · 2026
A18: Плитка і підлоги | B18: Плитка | C18: Укладання плитки 300х300 | D18: м² | E18: 641 | F18: 500 | G18: 820 | H18: 985 | I18: підняти | J18: 800 | K18: =IF(AND(ISNUMBER(J18),E18>0),J18/E18-1,"") -> 0.24804992 | N18: =IF(L18="Своя ціна",M18,IF(L18="Прийняти",IF(ISNUMBER(J18),J18,E18),E18)) -> 641 | O18: Окремої ціни на 300х300 мало; порівняно з базовою ціною укладання на підлогу/стіни. | P18: https://plitka.ua/ua/services/ukladannya-plitki/ · 300х300 500 грн/м² (2025) · Київ · 2025 https://plitochnik.kiev.ua/ua/%D0%B2%D0%B0%D1%80%D1%82%D1%96%D1%81%D1%82%D1%8C-%D1%80%D0%BE%D0%B1%D1%96%D1%82-%D0%BF%D0%BB%D0%B8%D1%82%D0%BE%D1%87%D0%BD%D0%B8%D0%BA%D0%B0.html · кераміка до 600 мм 720 грн/м² · Київ · 2026 https://www.rabotniki.ua/uk/price/ukladka-plitki-na-pol/kiev · підлога сер. 985 грн/м² · Київ · 25.10.2026 https://www.rabotniki.ua/uk/plitochnye-raboty · підлога сер. 905 · Україна (агрегат) · 2026 https://kabanchik.ua/ua/kyiv/category/ukladannia-plytky · підлога 820 · Київ · 10.2026 https://bud.arsel.com.ua/tsiny-na-budivelni-roboty/ · підлога 900 · Київ і обл. · 01.01.2026 https://liv-comfort.kyiv.ua/price-remont/index.html · підлога 750 · Київ · 2026
A19: Плитка і підлоги | B19: Плитка | C19: Укладання плитки 300х600 | D19: м² | E19: 594 | F19: 500 | G19: 850 | H19: 1033 | I19: підняти | J19: 850 | K19: =IF(AND(ISNUMBER(J19),E19>0),J19/E19-1,"") -> 0.43097643 | N19: =IF(L19="Своя ціна",M19,IF(L19="Прийняти",IF(ISNUMBER(J19),J19,E19),E19)) -> 594 | O19: Типовий настінний формат; ринок 700–1000 у більшості джерел. Наші 594 — на рівні мінімумів. | P19: https://www.rabotniki.ua/uk/plitochnye-raboty · стіни 500/933/1550 грн/м² · Україна (агрегат) · 2026 https://www.rabotniki.ua/uk/price/ukladka-plitki-na-pol/kiev · стіни сер. 1033 грн/м² · Київ · 25.10.2026 https://www.rabotniki.ua/uk/plitochnye-raboty/lvov · стіни 750/963/1300 грн/м² · Львів · 2026 https://kabanchik.ua/ua/kyiv/category/ukladannia-plytky · стіни (проста укладка) 840 грн/м² · Київ · 10.2026 https://plitochnik.kiev.ua/ua/%D0%B2%D0%B0%D1%80%D1%82%D1%96%D1%81%D1%82%D1%8C-%D1%80%D0%BE%D0%B1%D1%96%D1%82-%D0%BF%D0%BB%D0%B8%D1%82%D0%BE%D1%87%D0%BD%D0%B8%D0%BA%D0%B0.html · керамічна плитка до 600 мм 720 грн/м² · Київ · 2026 https://plitka.ua/ua/services/ukladannya-plitki/ · 300х600 500 грн/м² (2025) · Київ · 2025 https://bud.arsel.com.ua/tsiny-na-budivelni-roboty/ · плитка на стіни 900 грн/м² · Київ і обл. · 01.01.2026 https://liv-comfort.kyiv.ua/price-remont/index.html · плитка стіни/укоси 850 грн/м² · Київ · 2026 https://remmo.lviv.ua/plytochni-roboty-lviv/ · укладання плитки на стіни 700 грн/м² · Львів · 25.01.2026 https://www.remonthub.org/prices.php · укладка плитки 850 грн/м² · Київ · 2026 https://stroyremdizayn.kiev.ua/rascenki-na-otdelochnye-raboty.html · керамічна плитка 850 грн/м² · Київ · 2026
A20: Плитка і підлоги | B20: Плитка | C20: Укладання плитки 600х1200 | D20: м² | E20: 732 | F20: 800 | G20: 876 | H20: 950 | I20: підняти | J20: 880 | K20: =IF(AND(ISNUMBER(J20),E20>0),J20/E20-1,"") -> 0.20218579 | N20: =IF(L20="Своя ціна",M20,IF(L20="Прийняти",IF(ISNUMBER(J20),J20,E20),E20)) -> 732 | O20: DF: доплата за великий формат +20–30% (Київ) до базової 800–1400. | P20: https://plitka.ua/ua/services/ukladannya-plitki/ · 600х1200 800 грн/м² (2025) · Київ · 2025 https://stroyremdizayn.kiev.ua/rascenki-na-otdelochnye-raboty.html · 1200×600 950 грн/м² · Київ · 2026 https://plitochnik.kiev.ua/ua/%D0%B2%D0%B0%D1%80%D1%82%D1%96%D1%81%D1%82%D1%8C-%D1%80%D0%BE%D0%B1%D1%96%D1%82-%D0%BF%D0%BB%D0%B8%D1%82%D0%BE%D1%87%D0%BD%D0%B8%D0%BA%D0%B0.html · середній формат від 816 грн/м² · Київ · 2026 https://plitochnik.kiev.ua/ua/%D0%B2%D0%B0%D1%80%D1%82%D1%96%D1%81%D1%82%D1%8C-%D1%80%D0%BE%D0%B1%D1%96%D1%82-%D0%BF%D0%BB%D0%B8%D1%82%D0%BE%D1%87%D0%BD%D0%B8%D0%BA%D0%B0.html · великий формат від 936 грн/м² · Київ · 2026
A21: Плитка і підлоги | B21: Плитка | C21: Укладання плитки 600х600 | D21: м² | E21: 631 | F21: 600 | G21: 835 | H21: 985 | I21: підняти | J21: 830 | K21: =IF(AND(ISNUMBER(J21),E21>0),J21/E21-1,"") -> 0.31537242 | N21: =IF(L21="Своя ціна",M21,IF(L21="Прийняти",IF(ISNUMBER(J21),J21,E21),E21)) -> 631 | O21: Базовий формат підлоги. Наша ціна нижча за всі джерела, крім plitka.ua (2025). DF: Київ 800–1400, Львів 550–800, інші міста 450–900. | P21: https://www.rabotniki.ua/uk/price/ukladka-plitki-na-pol/kiev · укладання плитки на підлогу: 550/985/1500 грн/м² (мін/сер/макс) · Київ · 25.10.2026 https://www.rabotniki.ua/uk/plitochnye-raboty/lvov · підлога 550/888/1300 грн/м² · Львів · 2026 https://www.rabotniki.ua/uk/plitochnye-raboty · підлога 500/905/1500 грн/м² · Україна (агрегат) · 2026 https://kabanchik.ua/ua/kyiv/category/ukladannia-plytky · укладання плитки на підлогу 820 грн/м² (блок 'Вартість послуг') · Київ · 10.2026 https://plitochnik.kiev.ua/ua/%D0%B2%D0%B0%D1%80%D1%82%D1%96%D1%81%D1%82%D1%8C-%D1%80%D0%BE%D0%B1%D1%96%D1%82-%D0%BF%D0%BB%D0%B8%D1%82%D0%BE%D1%87%D0%BD%D0%B8%D0%BA%D0%B0.html · керамограніт до 600 мм 744 грн/м² · Київ · 2026 https://stroyremdizayn.kiev.ua/rascenki-na-otdelochnye-raboty.html · 600х600 850 грн/м² · Київ · 2026 https://plitka.ua/ua/services/ukladannya-plitki/ · 600х600 600 грн/м² (2025) · Київ · 2025 https://bud.arsel.com.ua/tsiny-na-budivelni-roboty/ · плитка на підлогу 900 грн/м² · Київ і обл. · 01.01.2026 https://liv-comfort.kyiv.ua/price-remont/index.html · плитка підлога 750 грн/м² · Київ · 2026 https://remmo.lviv.ua/plytochni-roboty-lviv/ · керамограніт від 700 грн/м² · Львів · 25.01.2026
A22: Плитка і підлоги | B22: Плитка | C22: Укладання плитки 800х800 | D22: м² | E22: 779 | F22: 816 | G22: 900 | H22: 950 | I22: підняти | J22: 900 | K22: =IF(AND(ISNUMBER(J22),E22>0),J22/E22-1,"") -> 0.15532734 | N22: =IF(L22="Своя ціна",M22,IF(L22="Прийняти",IF(ISNUMBER(J22),J22,E22),E22)) -> 779 | P22: https://stroyremdizayn.kiev.ua/rascenki-na-otdelochnye-raboty.html · 800×800 950 грн/м² · Київ · 2026 https://plitka.ua/ua/services/ukladannya-plitki/ · 800х800 900 грн/м² (2025) · Київ · 2025 https://plitochnik.kiev.ua/ua/%D0%B2%D0%B0%D1%80%D1%82%D1%96%D1%81%D1%82%D1%8C-%D1%80%D0%BE%D0%B1%D1%96%D1%82-%D0%BF%D0%BB%D0%B8%D1%82%D0%BE%D1%87%D0%BD%D0%B8%D0%BA%D0%B0.html · середній формат від 816 грн/м² · Київ · 2026
A23: Плитка і підлоги | B23: Плитка | C23: Укладання плитки кабанчик, «цегла» | D23: м² | E23: 998 | F23: 620 | G23: 1297 | H23: 1513 | I23: підняти | J23: 1300 | K23: =IF(AND(ISNUMBER(J23),E23>0),J23/E23-1,"") -> 0.30260521 | N23: =IF(L23="Своя ціна",M23,IF(L23="Прийняти",IF(ISNUMBER(J23),J23,E23),E23)) -> 998 | O23: Одна з найбільших розбіжностей: усі джерела 2026 року дають 1200–1500. | P23: https://www.rabotniki.ua/uk/plitochnye-raboty · «кабанчик» 750/1294/2000 грн/м² · Україна (агрегат) · 2026 https://www.rabotniki.ua/uk/price/ukladka-plitki-na-pol/kiev · «кабанчик» сер. 1334 грн/м² · Київ · 25.10.2026 https://budver.com/masters/ukladannya-plitki-kabanchik · 825/1513/2200 грн/м² · Україна (агрегат) · 2026 https://kabanchik.ua/ua/kyiv/category/ukladannia-plytky · «кабанчик» 1200 грн/м² · Київ · 10.2026 https://stroyremdizayn.kiev.ua/rascenki-na-otdelochnye-raboty.html · «кабанчик» 1300 грн/м² · Київ · 2026 https://plitka.ua/ua/services/ukladannya-plitki/ · кабанчик 620 грн/м² (2025) · Київ · 2025
A24: Плитка і підлоги | B24: Підлоги | C24: Монтаж міжкімнатного порога | D24: м.п. | E24: 400 | F24: 150 | G24: 209 | H24: 215 | I24: знизити | J24: 210 | K24: =IF(AND(ISNUMBER(J24),E24>0),J24/E24-1,"") -> -0.475 | N24: =IF(L24="Своя ціна",M24,IF(L24="Прийняти",IF(ISNUMBER(J24),J24,E24),E24)) -> 400 | O24: Удвічі дорожче за перехідний профіль (200). Для порога краще одиниця PIECE. | P24: https://www.rabotniki.ua/uk/price/ukladka-laminata-price/kiev · прямий поріжок 215 грн/м.п. · Київ · 25.10.2026 https://www.rabotniki.ua/uk/price/tsiklevanie-parketa-pokrytie-lakom · 209 · Україна (агрегат) · 25.10.2026 https://www.remonthub.org/prices.php · порогова планка 150 · Київ · 2026
A25: Плитка і підлоги | B25: Підлоги | C25: Монтаж утеплювача під стяжку | D25: м² | E25: 302 | F25: 130 | G25: 145 | H25: 160 | I25: знизити | J25: 160 | K25: =IF(AND(ISNUMBER(J25),E25>0),J25/E25-1,"") -> -0.47019868 | N25: =IF(L25="Своя ціна",M25,IF(L25="Прийняти",IF(ISNUMBER(J25),J25,E25),E25)) -> 302 | O25: Сусідня позиція 'Монтаж утеплювача' коштує 130, тобто ця завищена. | P25: https://www.rabotniki.ua/uk/chernovye-raboty-po-polu/kiev · утеплення стиродуром 130/160/200 грн/м² · Київ · 2026 https://bud.arsel.com.ua/tsiny-na-budivelni-roboty/ · утеплювач під стяжку 130 · Київ і обл. · 01.01.2026
A26: Плитка і підлоги | B26: Підлоги | C26: Плівкова ізоляція під стяжку | D26: м² | E26: 134 | F26: 60 | G26: 60 | H26: 64 | I26: знизити | J26: 60 | K26: =IF(AND(ISNUMBER(J26),E26>0),J26/E26-1,"") -> -0.55223881 | N26: =IF(L26="Своя ціна",M26,IF(L26="Прийняти",IF(ISNUMBER(J26),J26,E26),E26)) -> 134 | O26: Удвічі вище за ринок. | P26: https://www.rabotniki.ua/uk/chernovye-raboty-po-polu/kiev · плівкова гідроізоляція 40/64/80 грн/м² · Київ · 2026 https://bud.arsel.com.ua/tsiny-na-budivelni-roboty/ · плівкова гідроізоляція 60 · Київ і обл. · 01.01.2026 https://stroyremdizayn.kiev.ua/rascenki-na-otdelochnye-raboty.html · плівка 60 · Київ · 2026
A27: Плитка і підлоги | B27: Підлоги | C27: Укладання фанери або OSB на стяжку чи лаги | D27: м² | E27: 250 | F27: 175 | G27: 202 | H27: 217 | I27: знизити | J27: 210 | K27: =IF(AND(ISNUMBER(J27),E27>0),J27/E27-1,"") -> -0.16 | N27: =IF(L27="Своя ціна",M27,IF(L27="Прийняти",IF(ISNUMBER(J27),J27,E27),E27)) -> 250 | O27: Небагато вище за ринок. | P27: https://www.rabotniki.ua/uk/price/ukladka-laminata-price/kiev · фанера Київ 217 · Київ · 25.10.2026 https://www.rabotniki.ua/uk/price/tsiklevanie-parketa-pokrytie-lakom · фанера Україна 202 · Україна (агрегат) · 25.10.2026 https://rating-remont-kvartir.com.ua/ua/rozcinki-na-roboti-z-pidlogami-lviv/ · фанера на лаги 150–200 (Львів) · Львів · 07.01.2026
A28: Плитка і підлоги | B28: Плитка | C28: Шліфування стяжки (зняття перепадів до 5 мм) | D28: м² | E28: 392 | F28: 180 | G28: 203 | H28: 226 | I28: знизити | J28: 230 | K28: =IF(AND(ISNUMBER(J28),E28>0),J28/E28-1,"") -> -0.41326531 | N28: =IF(L28="Своя ціна",M28,IF(L28="Прийняти",IF(ISNUMBER(J28),J28,E28),E28)) -> 392 | O28: FLOORING 'Шліфування бетонної основи' — 150. | P28: https://www.rabotniki.ua/uk/chernovye-raboty-po-polu/kiev · шліфування стяжки 180/226/280 грн/м² · Київ · 2026 https://plitochnik.kiev.ua/ua/%D0%B2%D0%B0%D1%80%D1%82%D1%96%D1%81%D1%82%D1%8C-%D1%80%D0%BE%D0%B1%D1%96%D1%82-%D0%BF%D0%BB%D0%B8%D1%82%D0%BE%D1%87%D0%BD%D0%B8%D0%BA%D0%B0.html · шліфування, зняття молочка від 180 · Київ · 2026
A29: Плитка і підлоги | B29: Підлоги | C29: Укладання ламінату ялинкою | D29: м² | E29: 500 | F29: 700 | G29: 700 | H29: 700 | I29: неясно | K29: =IF(AND(ISNUMBER(J29),E29>0),J29/E29-1,"") | N29: =IF(L29="Своя ціна",M29,IF(L29="Прийняти",IF(ISNUMBER(J29),J29,E29),E29)) -> 500 | O29: Лише одне джерело (700). Можливо, ціну занижено. | P29: https://parket-doska.com.ua/ukladannya-parketu-iz-zavodskoyu-obrobkoyu-malyunok-francuzka-rizka-ugorska-yalinka-na-styazhku/ · ламінат ялинкою 700 грн/м² · Київ · н/д
A30: Плитка і підлоги | B30: Плитка | C30: Нанесення двокомпонентної гідроізоляції | D30: м² | E30: 273 | F30: 292 | G30: 366 | H30: 440 | I30: неясно | K30: =IF(AND(ISNUMBER(J30),E30>0),J30/E30-1,"") | N30: =IF(L30="Своя ціна",M30,IF(L30="Прийняти",IF(ISNUMBER(J30),J30,E30),E30)) -> 273 | O30: Пряме порівняння є лише одне (PK 440). Схоже, що ціну варто підняти до ~350–400. | P30: https://plitochnik.kiev.ua/ua/%D0%B2%D0%B0%D1%80%D1%82%D1%96%D1%81%D1%82%D1%8C-%D1%80%D0%BE%D0%B1%D1%96%D1%82-%D0%BF%D0%BB%D0%B8%D1%82%D0%BE%D1%87%D0%BD%D0%B8%D0%BA%D0%B0.html · двокомпонентна 2 шари 440 грн/м² · Київ · 2026 https://budver.com/masters/vlashtuvannya-gidroizolyacii-pid-plitkoyu · гідроізоляція під плиткою (тип не вказано) сер. 292 · Україна (агрегат) · 2026
A31: Плитка і підлоги | B31: Підлоги | C31: Армування підлоги сіткою під стяжку | D31: м² | E31: 130 | F31: 85 | G31: 109 | H31: 126 | I31: в ринку | K31: =IF(AND(ISNUMBER(J31),E31>0),J31/E31-1,"") | N31: =IF(L31="Своя ціна",M31,IF(L31="Прийняти",IF(ISNUMBER(J31),J31,E31),E31)) -> 130 | P31: https://www.rabotniki.ua/uk/chernovye-raboty-po-polu/kiev · сітка 100/126/170 грн/м² · Київ · 2026 https://www.rabotniki.ua/uk/chernovye-raboty-po-polu/kiev · армування 113 · Київ · 2026 https://bud.arsel.com.ua/tsiny-na-budivelni-roboty/ · сітка 85 · Київ і обл. · 01.01.2026 https://bud.arsel.com.ua/tsiny-na-budivelni-roboty/ · армування 105 · Київ і обл. · 01.01.2026
A32: Плитка і підлоги | B32: Підлоги | C32: Вирівнювання підлоги самовирівнюючим розчином | D32: м² | E32: 300 | F32: 250 | G32: 300 | H32: 400 | I32: в ринку | K32: =IF(AND(ISNUMBER(J32),E32>0),J32/E32-1,"") | N32: =IF(L32="Своя ціна",M32,IF(L32="Прийняти",IF(ISNUMBER(J32),J32,E32),E32)) -> 300 | O32: Дублі: TILING 'Влаштування наливної підлоги' 255 і FLOORING 'Наливна підлога — вирівнювальний шар 10–50 мм' 279. Усі в межах ринку. | P32: https://www.rabotniki.ua/uk/chernovye-raboty-po-polu/kiev · 180/335/450 грн/м² · Київ · 2026 https://bud.arsel.com.ua/tsiny-na-budivelni-roboty/ · 260 · Київ і обл. · 01.01.2026 https://plitochnik.kiev.ua/ua/%D0%B2%D0%B0%D1%80%D1%82%D1%96%D1%81%D1%82%D1%8C-%D1%80%D0%BE%D0%B1%D1%96%D1%82-%D0%BF%D0%BB%D0%B8%D1%82%D0%BE%D1%87%D0%BD%D0%B8%D0%BA%D0%B0.html · 300 · Київ · 2026 https://mirafloor.com.ua/statti/nalivna-pidloga-tsina-za-m2.html · від 350 (тільки робота) · Київ · 09.2026 https://stroyremdizayn.kiev.ua/rascenki-na-otdelochnye-raboty.html · 250 · Київ · 2026 https://remmo.lviv.ua/plytochni-roboty-lviv/ · 250 · Львів · 25.01.2026 https://www.remonthub.org/prices.php · 400 · Київ · 2026
A33: Плитка і підлоги | B33: Підлоги | C33: Монтаж перехідного (стикового) профілю між покриттями | D33: м.п. | E33: 200 | F33: 150 | G33: 209 | H33: 215 | I33: в ринку | K33: =IF(AND(ISNUMBER(J33),E33>0),J33/E33-1,"") | N33: =IF(L33="Своя ціна",M33,IF(L33="Прийняти",IF(ISNUMBER(J33),J33,E33),E33)) -> 200 | P33: https://www.rabotniki.ua/uk/price/ukladka-laminata-price/kiev · прямий поріжок 215 · Київ · 25.10.2026 https://www.rabotniki.ua/uk/price/tsiklevanie-parketa-pokrytie-lakom · 209 · Україна (агрегат) · 25.10.2026 https://www.remonthub.org/prices.php · порогова планка 150 · Київ · 2026
A34: Плитка і підлоги | B34: Підлоги | C34: Монтаж плінтуса дерев'яного | D34: м.п. | E34: 250 | F34: 175 | G34: 248 | H34: 262 | I34: в ринку | K34: =IF(AND(ISNUMBER(J34),E34>0),J34/E34-1,"") | N34: =IF(L34="Своя ціна",M34,IF(L34="Прийняти",IF(ISNUMBER(J34),J34,E34),E34)) -> 250 | P34: https://www.rabotniki.ua/uk/price/ukladka-laminata-price/kiev · Київ 262 · Київ · 25.10.2026 https://www.rabotniki.ua/uk/price/tsiklevanie-parketa-pokrytie-lakom · 247 · Україна (агрегат) · 25.10.2026 https://stroyremdizayn.kiev.ua/rascenki-na-otdelochnye-raboty.html · 250 · Київ · 2026 https://bud.arsel.com.ua/tsiny-na-budivelni-roboty/ · 175 · Київ і обл. · 01.01.2026
A35: Плитка і підлоги | B35: Підлоги | C35: Монтаж плінтуса пластик | D35: м.п. | E35: 150 | F35: 80 | G35: 135 | H35: 150 | I35: в ринку | K35: =IF(AND(ISNUMBER(J35),E35>0),J35/E35-1,"") | N35: =IF(L35="Своя ціна",M35,IF(L35="Прийняти",IF(ISNUMBER(J35),J35,E35),E35)) -> 150 | P35: https://www.rabotniki.ua/uk/price/ukladka-laminata-price/kiev · Київ 148 · Київ · 25.10.2026 https://www.rabotniki.ua/uk/price/tsiklevanie-parketa-pokrytie-lakom · 140 · Україна (агрегат) · 25.10.2026 https://stroyremdizayn.kiev.ua/rascenki-na-otdelochnye-raboty.html · 150 · Київ · 2026 https://liv-comfort.kyiv.ua/price-remont/index.html · 80 · Київ · 2026 https://bud.arsel.com.ua/tsiny-na-budivelni-roboty/ · 130 · Київ і обл. · 01.01.2026 https://www.remonthub.org/prices.php · 120 · Київ · 2026
A36: Плитка і підлоги | B36: Підлоги | C36: Монтаж плінтуса шпонованого МДФ | D36: м.п. | E36: 280 | F36: 215 | G36: 261 | H36: 280 | I36: в ринку | K36: =IF(AND(ISNUMBER(J36),E36>0),J36/E36-1,"") | N36: =IF(L36="Своя ціна",M36,IF(L36="Прийняти",IF(ISNUMBER(J36),J36,E36),E36)) -> 280 | P36: https://www.rabotniki.ua/uk/price/ukladka-laminata-price/kiev · МДФ Київ 270 · Київ · 25.10.2026 https://www.rabotniki.ua/uk/price/tsiklevanie-parketa-pokrytie-lakom · 261 · Україна (агрегат) · 25.10.2026 https://stroyremdizayn.kiev.ua/rascenki-na-otdelochnye-raboty.html · 280 · Київ · 2026 https://liv-comfort.kyiv.ua/price-remont/index.html · МДФ/поліуретан 250 · Київ · 2026 https://bud.arsel.com.ua/tsiny-na-budivelni-roboty/ · МДФ 215 · Київ і обл. · 01.01.2026
A37: Плитка і підлоги | B37: Підлоги | C37: Настил лінолеуму ковроліну | D37: м² | E37: 200 | F37: 150 | G37: 198 | H37: 250 | I37: в ринку | K37: =IF(AND(ISNUMBER(J37),E37>0),J37/E37-1,"") | N37: =IF(L37="Своя ціна",M37,IF(L37="Прийняти",IF(ISNUMBER(J37),J37,E37),E37)) -> 200 | P37: https://www.rabotniki.ua/uk/price/ukladka-laminata-price/kiev · без клею 207 · Київ · 25.10.2026 https://www.rabotniki.ua/uk/price/tsiklevanie-parketa-pokrytie-lakom · 196 · Україна (агрегат) · 25.10.2026 https://stroyremdizayn.kiev.ua/rascenki-na-otdelochnye-raboty.html · 200 · Київ · 2026 https://liv-comfort.kyiv.ua/price-remont/index.html · 250 · Київ · 2026 https://bud.arsel.com.ua/tsiny-na-budivelni-roboty/ · 150 · Київ і обл. · 01.01.2026 https://www.remonthub.org/prices.php · 190 · Київ · 2026
A38: Плитка і підлоги | B38: Підлоги | C38: Стяжка з керамзитом | D38: м² | E38: 421 | F38: 390 | G38: 423 | H38: 456 | I38: в ринку | K38: =IF(AND(ISNUMBER(J38),E38>0),J38/E38-1,"") | N38: =IF(L38="Своя ціна",M38,IF(L38="Прийняти",IF(ISNUMBER(J38),J38,E38),E38)) -> 421 | P38: https://www.rabotniki.ua/uk/chernovye-raboty-po-polu/kiev · 400/456/500 грн/м² · Київ · 2026 https://bud.arsel.com.ua/tsiny-na-budivelni-roboty/ · 390 · Київ і обл. · 01.01.2026
A39: Плитка і підлоги | B39: Підлоги | C39: Укладання замкового кварцвінілу (SPC) на підкладку | D39: м² | E39: 350 | F39: 350 | G39: 350 | H39: 450 | I39: в ринку | K39: =IF(AND(ISNUMBER(J39),E39>0),J39/E39-1,"") | N39: =IF(L39="Своя ціна",M39,IF(L39="Прийняти",IF(ISNUMBER(J39),J39,E39),E39)) -> 350 | P39: https://stroyremdizayn.kiev.ua/rascenki-na-otdelochnye-raboty.html · на підкладку 350 · Київ · 2026 https://liv-comfort.kyiv.ua/price-remont/index.html · замковий 350 · Київ · 2026 https://parket-doska.com.ua/ukladannya-parketu-iz-zavodskoyu-obrobkoyu-malyunok-francuzka-rizka-ugorska-yalinka-na-styazhku/ · плаваючий 'палуба' 450 · Київ · н/д
A40: Плитка і підлоги | B40: Підлоги | C40: Укладання клейового кварцвінілу (LVT) на клей | D40: м² | E40: 420 | F40: 320 | G40: 410 | H40: 550 | I40: в ринку | K40: =IF(AND(ISNUMBER(J40),E40>0),J40/E40-1,"") | N40: =IF(L40="Своя ціна",M40,IF(L40="Прийняти",IF(ISNUMBER(J40),J40,E40),E40)) -> 420 | P40: https://stroyremdizayn.kiev.ua/rascenki-na-otdelochnye-raboty.html · на клей 420 · Київ · 2026 https://liv-comfort.kyiv.ua/price-remont/index.html · клейовий 400 · Київ · 2026 https://parket-doska.com.ua/ukladannya-parketu-iz-zavodskoyu-obrobkoyu-malyunok-francuzka-rizka-ugorska-yalinka-na-styazhku/ · клейовий 'палуба' 550 · Київ · н/д https://bud.arsel.com.ua/tsiny-na-budivelni-roboty/ · вінілова плитка 320 · Київ і обл. · 01.01.2026
A41: Плитка і підлоги | B41: Підлоги | C41: Укладання ламінату по діагоналі | D41: м² | E41: 350 | F41: 170 | G41: 350 | H41: 400 | I41: в ринку | K41: =IF(AND(ISNUMBER(J41),E41>0),J41/E41-1,"") | N41: =IF(L41="Своя ціна",M41,IF(L41="Прийняти",IF(ISNUMBER(J41),J41,E41),E41)) -> 350 | P41: https://stroyremdizayn.kiev.ua/rascenki-na-otdelochnye-raboty.html · 400 · Київ · 2026 https://liv-comfort.kyiv.ua/price-remont/index.html · 400 · Київ · 2026 https://bud.arsel.com.ua/tsiny-na-budivelni-roboty/ · 260 · Київ і обл. · 01.01.2026 https://kabanchik.ua/ua/kyiv/category/ukladannia-laminatu · діагональ 170 · Київ · 10.2026 https://www.remonthub.org/prices.php · 350 · Київ · 2026
A42: Плитка і підлоги | B42: Підлоги | C42: Укладання ламінату прямим способом | D42: м² | E42: 300 | F42: 190 | G42: 301 | H42: 350 | I42: в ринку | K42: =IF(AND(ISNUMBER(J42),E42>0),J42/E42-1,"") | N42: =IF(L42="Своя ціна",M42,IF(L42="Прийняти",IF(ISNUMBER(J42),J42,E42),E42)) -> 300 | P42: https://www.rabotniki.ua/uk/price/ukladka-laminata-price/kiev · Київ 260/328/400 грн/м² · Київ · 25.10.2026 https://www.rabotniki.ua/uk/price/tsiklevanie-parketa-pokrytie-lakom · ламінат (Україна) 301 · Україна (агрегат) · 25.10.2026 https://stroyremdizayn.kiev.ua/rascenki-na-otdelochnye-raboty.html · 350 · Київ · 2026 https://liv-comfort.kyiv.ua/price-remont/index.html · 350 · Київ · 2026 https://bud.arsel.com.ua/tsiny-na-budivelni-roboty/ · 190 · Київ і обл. · 01.01.2026 https://kabanchik.ua/ua/kyiv/category/ukladannia-laminatu · 250 · Київ · 10.2026 https://www.remonthub.org/prices.php · 250 · Київ · 2026
A43: Плитка і підлоги | B43: Підлоги | C43: Укладання паркетної / інженерної дошки на клей | D43: м² | E43: 520 | F43: 435 | G43: 491 | H43: 551 | I43: в ринку | K43: =IF(AND(ISNUMBER(J43),E43>0),J43/E43-1,"") | N43: =IF(L43="Своя ціна",M43,IF(L43="Прийняти",IF(ISNUMBER(J43),J43,E43),E43)) -> 520 | P43: https://www.rabotniki.ua/uk/price/ukladka-laminata-price/kiev · Київ, паркетна дошка на клей 551 · Київ · 25.10.2026 https://www.rabotniki.ua/uk/price/tsiklevanie-parketa-pokrytie-lakom · Україна 491 · Україна (агрегат) · 25.10.2026 https://bud.arsel.com.ua/tsiny-na-budivelni-roboty/ · на клей 435 · Київ і обл. · 01.01.2026
A44: Плитка і підлоги | B44: Підлоги | C44: Укладання штучного паркету на клей (палуба, ялинка) | D44: м² | E44: 750 | F44: 700 | G44: 700 | H44: 700 | I44: в ринку | K44: =IF(AND(ISNUMBER(J44),E44>0),J44/E44-1,"") | N44: =IF(L44="Своя ціна",M44,IF(L44="Прийняти",IF(ISNUMBER(J44),J44,E44),E44)) -> 750 | O44: Одне джерело. | P44: https://parket-doska.com.ua/ukladannya-parketu-iz-zavodskoyu-obrobkoyu-malyunok-francuzka-rizka-ugorska-yalinka-na-styazhku/ · паркет ялинкою на стяжку 700 грн/м² · Київ · н/д
A45: Плитка і підлоги | B45: Підлоги | C45: Цементно-піщана стяжка понад 20м2 | D45: м² | E45: 400 | F45: 350 | G45: 400 | H45: 500 | I45: в ринку | K45: =IF(AND(ISNUMBER(J45),E45>0),J45/E45-1,"") | N45: =IF(L45="Своя ціна",M45,IF(L45="Прийняти",IF(ISNUMBER(J45),J45,E45),E45)) -> 400 | P45: https://www.rabotniki.ua/uk/chernovye-raboty-po-polu/kiev · ЦПС до 5 см сер. 396 · Київ · 2026 https://bud.arsel.com.ua/tsiny-na-budivelni-roboty/ · 350 · Київ і обл. · 01.01.2026 https://rbk-alba.com/ua/price · 450 · не вказано · 19.10.2026 https://plitochnik.kiev.ua/ua/%D0%B2%D0%B0%D1%80%D1%82%D1%96%D1%81%D1%82%D1%8C-%D1%80%D0%BE%D0%B1%D1%96%D1%82-%D0%BF%D0%BB%D0%B8%D1%82%D0%BE%D1%87%D0%BD%D0%B8%D0%BA%D0%B0.html · 480 · Київ · 2026 https://liv-comfort.kyiv.ua/price-remont/index.html · 400 · Київ · 2026 https://stroyremdizayn.kiev.ua/rascenki-na-otdelochnye-raboty.html · понад 20 м² 360 · Київ · 2026 https://www.remonthub.org/prices.php · 500 · Київ · 2026
A46: Плитка і підлоги | B46: Підлоги | C46: Циклювання паркету з лакуванням | D46: м² | E46: 737 | F46: 435 | G46: 738 | H46: 850 | I46: в ринку | K46: =IF(AND(ISNUMBER(J46),E46>0),J46/E46-1,"") | N46: =IF(L46="Своя ціна",M46,IF(L46="Прийняти",IF(ISNUMBER(J46),J46,E46),E46)) -> 737 | P46: https://www.rabotniki.ua/uk/price/tsiklevanie-parketa-pokrytie-lakom · 570/738/1000 грн/м² · Україна (агрегат) · 25.10.2026 https://parket-doska.com.ua/ukladannya-parketu-iz-zavodskoyu-obrobkoyu-malyunok-francuzka-rizka-ugorska-yalinka-na-styazhku/ · реставрація лак/олія 850 · Київ · н/д https://bud.arsel.com.ua/tsiny-na-budivelni-roboty/ · лакування 3 шари зі шпаклюванням 435 · Київ і обл. · 01.01.2026
A47: Плитка і підлоги | B47: Плитка | C47: Армування кутів гідроізоляційної стрічкою | D47: м.п. | E47: 119 | F47: 100 | G47: 140 | H47: 180 | I47: в ринку | K47: =IF(AND(ISNUMBER(J47),E47>0),J47/E47-1,"") | N47: =IF(L47="Своя ціна",M47,IF(L47="Прийняти",IF(ISNUMBER(J47),J47,E47),E47)) -> 119 | P47: https://plitochnik.kiev.ua/ua/%D0%B2%D0%B0%D1%80%D1%82%D1%96%D1%81%D1%82%D1%8C-%D1%80%D0%BE%D0%B1%D1%96%D1%82-%D0%BF%D0%BB%D0%B8%D1%82%D0%BE%D1%87%D0%BD%D0%B8%D0%BA%D0%B0.html · гідроізоляційна стрічка 180 грн/м.п. · Київ · 2026 https://stroyremdizayn.kiev.ua/rascenki-na-otdelochnye-raboty.html · монтаж стрічки 100 грн/м.п. · Київ · 2026
A48: Плитка і підлоги | B48: Плитка | C48: Виріз отворів більше 70 мм | D48: шт | E48: 283 | F48: 200 | G48: 280 | H48: 360 | I48: в ринку | K48: =IF(AND(ISNUMBER(J48),E48>0),J48/E48-1,"") | N48: =IF(L48="Своя ціна",M48,IF(L48="Прийняти",IF(ISNUMBER(J48),J48,E48),E48)) -> 283 | P48: https://plitochnik.kiev.ua/ua/%D0%B2%D0%B0%D1%80%D1%82%D1%96%D1%81%D1%82%D1%8C-%D1%80%D0%BE%D0%B1%D1%96%D1%82-%D0%BF%D0%BB%D0%B8%D1%82%D0%BE%D1%87%D0%BD%D0%B8%D0%BA%D0%B0.html · понад 70 мм 360 грн/шт · Київ · 2026 https://plitka.ua/ua/services/ukladannya-plitki/ · понад 70 мм 200 грн/шт (2025) · Київ · 2025
A49: Плитка і підлоги | B49: Плитка | C49: Влаштування люка ревізії на магнітах | D49: шт | E49: 1927 | F49: 1265 | G49: 2268 | H49: 2400 | I49: в ринку | K49: =IF(AND(ISNUMBER(J49),E49>0),J49/E49-1,"") | N49: =IF(L49="Своя ціна",M49,IF(L49="Прийняти",IF(ISNUMBER(J49),J49,E49),E49)) -> 1927 | O49: Нижче медіани, можна підняти до ~2200. | P49: https://www.rabotniki.ua/uk/plitochnye-raboty · 1150/2300/3500 грн/шт · Україна (агрегат) · 2026 https://www.rabotniki.ua/uk/price/ukladka-plitki-na-pol/kiev · сер. 2235 · Київ · 25.10.2026 https://budver.com/masters/plitochni-roboti · від 1265 · Україна (ціни 'від') · 2026 https://plitochnik.kiev.ua/ua/%D0%B2%D0%B0%D1%80%D1%82%D1%96%D1%81%D1%82%D1%8C-%D1%80%D0%BE%D0%B1%D1%96%D1%82-%D0%BF%D0%BB%D0%B8%D1%82%D0%BE%D1%87%D0%BD%D0%B8%D0%BA%D0%B0.html · від 2400 · Київ · 2026
A50: Плитка і підлоги | B50: Плитка | C50: Встановлення профілю для плитки | D50: м.п. | E50: 230 | F50: 110 | G50: 190 | H50: 324 | I50: в ринку | K50: =IF(AND(ISNUMBER(J50),E50>0),J50/E50-1,"") | N50: =IF(L50="Своя ціна",M50,IF(L50="Прийняти",IF(ISNUMBER(J50),J50,E50),E50)) -> 230 | P50: https://www.rabotniki.ua/uk/plitochnye-raboty · куточки 100/183/300 грн/м.п. · Україна (агрегат) · 2026 https://www.rabotniki.ua/uk/price/ukladka-plitki-na-pol/kiev · сер. 197 · Київ · 25.10.2026 https://kabanchik.ua/ua/kyiv/category/ukladannia-plytky · 160 · Київ · 10.2026 https://plitochnik.kiev.ua/ua/%D0%B2%D0%B0%D1%80%D1%82%D1%96%D1%81%D1%82%D1%8C-%D1%80%D0%BE%D0%B1%D1%96%D1%82-%D0%BF%D0%BB%D0%B8%D1%82%D0%BE%D1%87%D0%BD%D0%B8%D0%BA%D0%B0.html · кутовий профіль 264 · Київ · 2026 https://plitochnik.kiev.ua/ua/%D0%B2%D0%B0%D1%80%D1%82%D1%96%D1%81%D1%82%D1%8C-%D1%80%D0%BE%D0%B1%D1%96%D1%82-%D0%BF%D0%BB%D0%B8%D1%82%D0%BE%D1%87%D0%BD%D0%B8%D0%BA%D0%B0.html · прямий профіль 324 · Київ · 2026 https://budver.com/masters/plitochni-roboti · від 110 · Україна (ціни 'від') · 2026
A51: Плитка і підлоги | B51: Плитка | C51: Встановлення фризу, плінтуса | D51: м.п. | E51: 397 | F51: 360 | G51: 438 | H51: 600 | I51: в ринку | K51: =IF(AND(ISNUMBER(J51),E51>0),J51/E51-1,"") | N51: =IF(L51="Своя ціна",M51,IF(L51="Прийняти",IF(ISNUMBER(J51),J51,E51),E51)) -> 397 | P51: https://www.rabotniki.ua/uk/plitochnye-raboty · фриз до 100 мм 250/438/630 грн/м.п. · Україна (агрегат) · 2026 https://www.rabotniki.ua/uk/plitochnye-raboty · керамічний плінтус 300/525/800 · Україна (агрегат) · 2026 https://kabanchik.ua/ua/kyiv/category/ukladannia-plytky · керамічний плінтус 420 · Київ · 10.2026 https://plitochnik.kiev.ua/ua/%D0%B2%D0%B0%D1%80%D1%82%D1%96%D1%81%D1%82%D1%8C-%D1%80%D0%BE%D0%B1%D1%96%D1%82-%D0%BF%D0%BB%D0%B8%D1%82%D0%BE%D1%87%D0%BD%D0%B8%D0%BA%D0%B0.html · плінтус/фриз 360 · Київ · 2026 https://liv-comfort.kyiv.ua/price-remont/index.html · плитковий плінтус 600 · Київ · 2026 https://remmo.lviv.ua/plytochni-roboty-lviv/ · плитковий плінтус 500 · Львів · 25.01.2026 https://www.remonthub.org/prices.php · фриз 400 · Київ · 2026
A52: Плитка і підлоги | B52: Плитка | C52: Демонтаж плитки | D52: м² | E52: 224 | F52: 150 | G52: 176 | H52: 300 | I52: в ринку | K52: =IF(AND(ISNUMBER(J52),E52>0),J52/E52-1,"") | N52: =IF(L52="Своя ціна",M52,IF(L52="Прийняти",IF(ISNUMBER(J52),J52,E52),E52)) -> 224 | O52: DF: 150–300 грн/м². | P52: https://budver.com/masters/plitochni-roboti · від 176 грн/м² · Україна (ціни 'від') · 2026 https://rbk-alba.com/ua/price · з підлоги 300 / зі стін 250 · не вказано · 19.10.2026 https://plitochnik.kiev.ua/ua/%D0%B2%D0%B0%D1%80%D1%82%D1%96%D1%81%D1%82%D1%8C-%D1%80%D0%BE%D0%B1%D1%96%D1%82-%D0%BF%D0%BB%D0%B8%D1%82%D0%BE%D1%87%D0%BD%D0%B8%D0%BA%D0%B0.html · демонтаж покриття від 240 · Київ · 2026 https://bud.arsel.com.ua/tsiny-na-budivelni-roboty/ · 150 · Київ і обл. · 01.01.2026 https://remmo.lviv.ua/plytochni-roboty-lviv/ · 150 · Львів · 25.01.2026
A53: Плитка і підлоги | B53: Плитка | C53: Запил під 45° кута широкоформатної плитки | D53: м.п. | E53: 620 | F53: 550 | G53: 635 | H53: 720 | I53: в ринку | K53: =IF(AND(ISNUMBER(J53),E53>0),J53/E53-1,"") | N53: =IF(L53="Своя ціна",M53,IF(L53="Прийняти",IF(ISNUMBER(J53),J53,E53),E53)) -> 620 | P53: https://plitochnik.kiev.ua/ua/%D1%83%D0%BA%D0%BB%D0%B0%D0%B4%D0%B0%D0%BD%D0%BD%D1%8F-%D1%84%D0%BE%D1%80%D0%BC%D0%B0%D1%82%D0%BD%D0%BE%D0%B3%D0%BE-%D0%BA%D0%B5%D1%80%D0%B0%D0%BC%D0%BE%D0%B3%D1%80%D0%B0%D0%BD%D1%96%D1%82%D0%B0.html · 45° для широкого формату 720 грн/м.п. · Київ · 2026 https://stroyremdizayn.kiev.ua/rascenki-na-otdelochnye-raboty.html · великоформатний керамограніт 550 грн/м.п. · Київ · 2026
A54: Плитка і підлоги | B54: Плитка | C54: Заповнення товстого шва напівсухою сумішшю | D54: м² | E54: 229 | F54: 220 | G54: 242 | H54: 264 | I54: в ринку | K54: =IF(AND(ISNUMBER(J54),E54>0),J54/E54-1,"") | N54: =IF(L54="Своя ціна",M54,IF(L54="Прийняти",IF(ISNUMBER(J54),J54,E54),E54)) -> 229 | O54: rabotniki 154 грн/м.п. — інша одиниця. | P54: https://plitochnik.kiev.ua/ua/%D0%B2%D0%B0%D1%80%D1%82%D1%96%D1%81%D1%82%D1%8C-%D1%80%D0%BE%D0%B1%D1%96%D1%82-%D0%BF%D0%BB%D0%B8%D1%82%D0%BE%D1%87%D0%BD%D0%B8%D0%BA%D0%B0.html · напівсуха 264 грн/м² · Київ · 2026 https://stroyremdizayn.kiev.ua/rascenki-na-otdelochnye-raboty.html · суха суміш 220 грн/м² · Київ · 2026
A55: Плитка і підлоги | B55: Плитка | C55: Нанесення гідроізоляційної мастики у 2 шари | D55: м² | E55: 174 | F55: 120 | G55: 200 | H55: 292 | I55: в ринку | K55: =IF(AND(ISNUMBER(J55),E55>0),J55/E55-1,"") | N55: =IF(L55="Своя ціна",M55,IF(L55="Прийняти",IF(ISNUMBER(J55),J55,E55),E55)) -> 174 | O55: У межах, але нижче медіани (200). DF: 150–300. | P55: https://budver.com/masters/vlashtuvannya-gidroizolyacii-pid-plitkoyu · 165/292/418 грн/м² · Україна (агрегат) · 2026 https://plitochnik.kiev.ua/ua/%D0%B2%D0%B0%D1%80%D1%82%D1%96%D1%81%D1%82%D1%8C-%D1%80%D0%BE%D0%B1%D1%96%D1%82-%D0%BF%D0%BB%D0%B8%D1%82%D0%BE%D1%87%D0%BD%D0%B8%D0%BA%D0%B0.html · акрил/цемент 2 шари 264 · Київ · 2026 https://stroyremdizayn.kiev.ua/rascenki-na-otdelochnye-raboty.html · мастика 150 · Київ · 2026 https://liv-comfort.kyiv.ua/price-remont/index.html · 120 · Київ · 2026 https://bud.arsel.com.ua/tsiny-na-budivelni-roboty/ · фарбувальна від 200 · Київ і обл. · 01.01.2026 https://www.remonthub.org/prices.php · гідроізоляція підлог 2 шари 200 · Київ · 2026
A56: Плитка і підлоги | B56: Плитка | C56: Обробка захисною сумішшю, гідрофобізатором | D56: м² | E56: 131 | F56: 100 | G56: 110 | H56: 120 | I56: в ринку | K56: =IF(AND(ISNUMBER(J56),E56>0),J56/E56-1,"") | N56: =IF(L56="Своя ціна",M56,IF(L56="Прийняти",IF(ISNUMBER(J56),J56,E56),E56)) -> 131 | P56: https://plitochnik.kiev.ua/ua/%D0%B2%D0%B0%D1%80%D1%82%D1%96%D1%81%D1%82%D1%8C-%D1%80%D0%BE%D0%B1%D1%96%D1%82-%D0%BF%D0%BB%D0%B8%D1%82%D0%BE%D1%87%D0%BD%D0%B8%D0%BA%D0%B0.html · просочення/лак/гідрофоб 120 грн/м² · Київ · 2026 https://kabanchik.ua/ua/kyiv/category/ukladannia-plytky · гідрофобізація швів від 100 · Київ · 10.2026
A57: Плитка і підлоги | B57: Плитка | C57: Різ плитки під 90° зі шліфуванням (чистовий різ) | D57: м.п. | E57: 246 | F57: 250 | G57: 270 | H57: 326 | I57: в ринку | K57: =IF(AND(ISNUMBER(J57),E57>0),J57/E57-1,"") | N57: =IF(L57="Своя ціна",M57,IF(L57="Прийняти",IF(ISNUMBER(J57),J57,E57),E57)) -> 246 | O57: Біля нижньої межі (медіана ~270). | P57: https://www.rabotniki.ua/uk/plitochnye-raboty · різання+шліфування 170/300/450 грн/м.п. · Україна (агрегат) · 2026 https://www.rabotniki.ua/uk/price/ukladka-plitki-na-pol/kiev · сер. 326 · Київ · 25.10.2026 https://kabanchik.ua/ua/kyiv/category/ukladannia-plytky · 270 · Київ · 10.2026 https://bud.arsel.com.ua/tsiny-na-budivelni-roboty/ · 290 · Київ і обл. · 01.01.2026 https://plitochnik.kiev.ua/ua/%D0%B2%D0%B0%D1%80%D1%82%D1%96%D1%81%D1%82%D1%8C-%D1%80%D0%BE%D0%B1%D1%96%D1%82-%D0%BF%D0%BB%D0%B8%D1%82%D0%BE%D1%87%D0%BD%D0%B8%D0%BA%D0%B0.html · чистовий різ 264 · Київ · 2026 https://plitka.ua/ua/services/ukladannya-plitki/ · чистий різ 250 (2025) · Київ · 2025 https://remmo.lviv.ua/plytochni-roboty-lviv/ · прямий різ 250 · Львів · 25.01.2026
A58: Плитка і підлоги | B58: Плитка | C58: Укладання багатокутників: гексагон, стільники | D58: м² | E58: 952 | F58: 800 | G58: 928 | H58: 1056 | I58: в ринку | K58: =IF(AND(ISNUMBER(J58),E58>0),J58/E58-1,"") | N58: =IF(L58="Своя ціна",M58,IF(L58="Прийняти",IF(ISNUMBER(J58),J58,E58),E58)) -> 952 | P58: https://plitochnik.kiev.ua/ua/%D0%B2%D0%B0%D1%80%D1%82%D1%96%D1%81%D1%82%D1%8C-%D1%80%D0%BE%D0%B1%D1%96%D1%82-%D0%BF%D0%BB%D0%B8%D1%82%D0%BE%D1%87%D0%BD%D0%B8%D0%BA%D0%B0.html · гексагон 1056 грн/м² · Київ · 2026 https://plitka.ua/ua/services/ukladannya-plitki/ · гексагон/багатокутник 800 грн/м² (2025) · Київ · 2025
A59: Плитка і підлоги | B59: Плитка | C59: Укладання керамограніту 20 мм | D59: м² | E59: 1106 | F59: 1140 | G59: 1262 | H59: 1385 | I59: в ринку | K59: =IF(AND(ISNUMBER(J59),E59>0),J59/E59-1,"") | N59: =IF(L59="Своя ціна",M59,IF(L59="Прийняти",IF(ISNUMBER(J59),J59,E59),E59)) -> 1106 | P59: https://plitochnik.kiev.ua/ua/%D0%B2%D0%B0%D1%80%D1%82%D1%96%D1%81%D1%82%D1%8C-%D1%80%D0%BE%D0%B1%D1%96%D1%82-%D0%BF%D0%BB%D0%B8%D1%82%D0%BE%D1%87%D0%BD%D0%B8%D0%BA%D0%B0.html · керамограніт 20 мм 1140 грн/м² · Київ · 2026 https://www.rabotniki.ua/uk/plitochnye-raboty · керамограніт від 15 мм 800/1385/2000 · Україна (агрегат) · 2026
A60: Плитка і підлоги | B60: Плитка | C60: Укладання мозаїки | D60: м² | E60: 1115 | F60: 990 | G60: 1200 | H60: 2500 | I60: в ринку | K60: =IF(AND(ISNUMBER(J60),E60>0),J60/E60-1,"") | N60: =IF(L60="Своя ціна",M60,IF(L60="Прийняти",IF(ISNUMBER(J60),J60,E60),E60)) -> 1115 | O60: У межах діапазону, але нижче медіани (1200) і значно нижче середньої rabotniki (1743). Можна підняти до ~1200. | P60: https://www.rabotniki.ua/uk/plitochnye-raboty · стіни мозаїкою 1000/1743/2500 грн/м² · Україна (агрегат) · 2026 https://budver.com/masters/plitochni-roboti · мозаїка від 990 грн/м² · Україна (ціни 'від') · 2026 https://plitochnik.kiev.ua/ua/%D0%B2%D0%B0%D1%80%D1%82%D1%96%D1%81%D1%82%D1%8C-%D1%80%D0%BE%D0%B1%D1%96%D1%82-%D0%BF%D0%BB%D0%B8%D1%82%D0%BE%D1%87%D0%BD%D0%B8%D0%BA%D0%B0.html · мозаїка від 1140 грн/м² · Київ · 2026 https://stroyremdizayn.kiev.ua/rascenki-na-otdelochnye-raboty.html · мозаїка 2500 грн/м² · Київ · 2026 https://remmo.lviv.ua/plytochni-roboty-lviv/ · мозаїка на підлогу/стіни 1200 грн/м² · Львів · 25.01.2026
A61: Плитка і підлоги | B61: Плитка | C61: Укладання натурального каменю граніту, мармуру | D61: м² | E61: 1333 | F61: 1140 | G61: 1320 | H61: 1967 | I61: в ринку | K61: =IF(AND(ISNUMBER(J61),E61>0),J61/E61-1,"") | N61: =IF(L61="Своя ціна",M61,IF(L61="Прийняти",IF(ISNUMBER(J61),J61,E61),E61)) -> 1333 | P61: https://www.rabotniki.ua/uk/plitochnye-raboty · мармур/граніт 1200/1967/2705 грн/м² · Україна (агрегат) · 2026 https://budver.com/masters/plitochni-roboti · від 1320 грн/м² · Україна (ціни 'від') · 2026 https://plitochnik.kiev.ua/ua/%D0%B2%D0%B0%D1%80%D1%82%D1%96%D1%81%D1%82%D1%8C-%D1%80%D0%BE%D0%B1%D1%96%D1%82-%D0%BF%D0%BB%D0%B8%D1%82%D0%BE%D1%87%D0%BD%D0%B8%D0%BA%D0%B0.html · натуральний камінь від 1140 грн/м² · Київ · 2026
A62: Плитка і підлоги | B62: Плитка | C62: Укладання плитки 1000х1000 мм | D62: м² | E62: 918 | F62: 900 | G62: 1000 | H62: 1100 | I62: в ринку | K62: =IF(AND(ISNUMBER(J62),E62>0),J62/E62-1,"") | N62: =IF(L62="Своя ціна",M62,IF(L62="Прийняти",IF(ISNUMBER(J62),J62,E62),E62)) -> 918 | P62: https://stroyremdizayn.kiev.ua/rascenki-na-otdelochnye-raboty.html · 1000×1000 1100 грн/м² · Київ · 2026 https://plitka.ua/ua/services/ukladannya-plitki/ · 1000х1000 900 грн/м² (2025) · Київ · 2025
A63: Плитка і підлоги | B63: Плитка | C63: Укладання плитки 100х100 | D63: м² | E63: 911 | F63: 580 | G63: 842 | H63: 1250 | I63: в ринку | K63: =IF(AND(ISNUMBER(J63),E63>0),J63/E63-1,"") | N63: =IF(L63="Своя ціна",M63,IF(L63="Прийняти",IF(ISNUMBER(J63),J63,E63),E63)) -> 911 | O63: Великий розкид за джерелами. | P63: https://plitka.ua/ua/services/ukladannya-plitki/ · 100х100 580 грн/м² (2025) · Київ · 2025 https://remmo.lviv.ua/plytochni-roboty-lviv/ · плитка 10×10 700 грн/м² · Львів · 25.01.2026 https://plitochnik.kiev.ua/ua/%D0%B2%D0%B0%D1%80%D1%82%D1%96%D1%81%D1%82%D1%8C-%D1%80%D0%BE%D0%B1%D1%96%D1%82-%D0%BF%D0%BB%D0%B8%D1%82%D0%BE%D1%87%D0%BD%D0%B8%D0%BA%D0%B0.html · дрібна плитка 'цеглинка' 984 грн/м² · Київ · 2026 https://stroyremdizayn.kiev.ua/rascenki-na-otdelochnye-raboty.html · дрібноформатна 1250 грн/м² · Київ · 2026
A64: Плитка і підлоги | B64: Плитка | C64: Укладання плитки 1200х2400 мм | D64: м² | E64: 1837 | F64: 1920 | G64: 3210 | H64: 4500 | I64: в ринку | K64: =IF(AND(ISNUMBER(J64),E64>0),J64/E64-1,"") | N64: =IF(L64="Своя ціна",M64,IF(L64="Прийняти",IF(ISNUMBER(J64),J64,E64),E64)) -> 1837 | O64: SR — викид (4500); PK найближчий аналог. | P64: https://plitochnik.kiev.ua/ua/%D1%83%D0%BA%D0%BB%D0%B0%D0%B4%D0%B0%D0%BD%D0%BD%D1%8F-%D1%84%D0%BE%D1%80%D0%BC%D0%B0%D1%82%D0%BD%D0%BE%D0%B3%D0%BE-%D0%BA%D0%B5%D1%80%D0%B0%D0%BC%D0%BE%D0%B3%D1%80%D0%B0%D0%BD%D1%96%D1%82%D0%B0.html · 1200×2400 1920 грн/м² · Київ · 2026 https://stroyremdizayn.kiev.ua/rascenki-na-otdelochnye-raboty.html · 1200×2500 4500 грн/м² · Київ · 2026
A65: Плитка і підлоги | B65: Плитка | C65: Укладання плитки 1600х3200 мм | D65: м² | E65: 2742 | F65: 2640 | G65: 2640 | H65: 5000 | I65: в ринку | K65: =IF(AND(ISNUMBER(J65),E65>0),J65/E65-1,"") | N65: =IF(L65="Своя ціна",M65,IF(L65="Прийняти",IF(ISNUMBER(J65),J65,E65),E65)) -> 2742 | O65: Фактично одне порівнюване джерело. Решта наших великих форматів близька до прайсу plitochnik.kiev.ua (1000×2000 1680, 1000×3000 2160, 1200×3200 2400, 1500×3000 2200), тобто відхилення ±10%. | P65: https://plitochnik.kiev.ua/ua/%D1%83%D0%BA%D0%BB%D0%B0%D0%B4%D0%B0%D0%BD%D0%BD%D1%8F-%D1%84%D0%BE%D1%80%D0%BC%D0%B0%D1%82%D0%BD%D0%BE%D0%B3%D0%BE-%D0%BA%D0%B5%D1%80%D0%B0%D0%BC%D0%BE%D0%B3%D1%80%D0%B0%D0%BD%D1%96%D1%82%D0%B0.html · 1600×3200 2640 грн/м² · Київ · 2026 https://stroyremdizayn.kiev.ua/rascenki-na-otdelochnye-raboty.html · 1200×3000 5000 грн/м² (інший формат) · Київ · 2026
A66: Плитка і підлоги | B66: Плитка | C66: Укладання плитки 800х1600 | D66: м² | E66: 1077 | F66: 900 | G66: 936 | H66: 1100 | I66: в ринку | K66: =IF(AND(ISNUMBER(J66),E66>0),J66/E66-1,"") | N66: =IF(L66="Своя ціна",M66,IF(L66="Прийняти",IF(ISNUMBER(J66),J66,E66),E66)) -> 1077 | P66: https://plitka.ua/ua/services/ukladannya-plitki/ · 800х1600 900 грн/м² (2025) · Київ · 2025 https://plitochnik.kiev.ua/ua/%D0%B2%D0%B0%D1%80%D1%82%D1%96%D1%81%D1%82%D1%8C-%D1%80%D0%BE%D0%B1%D1%96%D1%82-%D0%BF%D0%BB%D0%B8%D1%82%D0%BE%D1%87%D0%BD%D0%B8%D0%BA%D0%B0.html · великий формат від 936 грн/м² · Київ · 2026 https://stroyremdizayn.kiev.ua/rascenki-na-otdelochnye-raboty.html · 1500×750 1100 грн/м² · Київ · 2026
A67: Плитка і підлоги | B67: Плитка | C67: Укладання плитки дошка до 1200 мм | D67: м² | E67: 756 | F67: 780 | G67: 800 | H67: 1267 | I67: в ринку | K67: =IF(AND(ISNUMBER(J67),E67>0),J67/E67-1,"") | N67: =IF(L67="Своя ціна",M67,IF(L67="Прийняти",IF(ISNUMBER(J67),J67,E67),E67)) -> 756 | O67: Наша ціна біля нижньої межі. | P67: https://plitochnik.kiev.ua/ua/%D0%B2%D0%B0%D1%80%D1%82%D1%96%D1%81%D1%82%D1%8C-%D1%80%D0%BE%D0%B1%D1%96%D1%82-%D0%BF%D0%BB%D0%B8%D1%82%D0%BE%D1%87%D0%BD%D0%B8%D0%BA%D0%B0.html · плитка під дерево до 1200 мм 780 грн/м² · Київ · 2026 https://plitka.ua/ua/services/ukladannya-plitki/ · дошка до 1200 800 грн/м² (2025) · Київ · 2025 https://www.rabotniki.ua/uk/plitochnye-raboty · керамічний паркет до 1200 мм сер. 1267 · Україна (агрегат) · 2026
A68: Плитка і підлоги | B68: Плитка | C68: Укладання ректифікованої плитки з мінімальним швом (1–1,5 мм) | D68: м² | E68: 1241 | F68: 880 | G68: 1118 | H68: 1366 | I68: в ринку | K68: =IF(AND(ISNUMBER(J68),E68>0),J68/E68-1,"") | N68: =IF(L68="Своя ціна",M68,IF(L68="Прийняти",IF(ISNUMBER(J68),J68,E68),E68)) -> 1241 | O68: PK: +30% до базової для шва 0,5 мм. | P68: https://www.rabotniki.ua/uk/plitochnye-raboty · ректифікована 750/1118/1565 грн/м² · Україна (агрегат) · 2026 https://www.rabotniki.ua/uk/plitochnye-raboty · безшовна 800/1366/2000 грн/м² · Україна (агрегат) · 2026 https://budver.com/masters/plitochni-roboti · безшовне від 880 грн/м² · Україна (ціни 'від') · 2026
A69: Плитка і підлоги | B69: Плитка | C69: Ґрунтування поверхні | D69: м² | E69: 35 | F69: 25 | G69: 38 | H69: 48 | I69: в ринку | K69: =IF(AND(ISNUMBER(J69),E69>0),J69/E69-1,"") | N69: =IF(L69="Своя ціна",M69,IF(L69="Прийняти",IF(ISNUMBER(J69),J69,E69),E69)) -> 35 | P69: https://www.rabotniki.ua/uk/plitochnye-raboty · 25/41/60 грн/м² · Україна (агрегат) · 2026 https://www.rabotniki.ua/uk/price/ukladka-plitki-na-pol/kiev · 47 · Київ · 25.10.2026 https://budver.com/masters/plitochni-roboti · від 27 · Україна (ціни 'від') · 2026 https://bud.arsel.com.ua/tsiny-na-budivelni-roboty/ · 35 · Київ і обл. · 01.01.2026 https://plitochnik.kiev.ua/ua/%D0%B2%D0%B0%D1%80%D1%82%D1%96%D1%81%D1%82%D1%8C-%D1%80%D0%BE%D0%B1%D1%96%D1%82-%D0%BF%D0%BB%D0%B8%D1%82%D0%BE%D1%87%D0%BD%D0%B8%D0%BA%D0%B0.html · 48 · Київ · 2026 https://remmo.lviv.ua/plytochni-roboty-lviv/ · 25 · Львів · 25.01.2026
A70: Малярка і гіпсокартон | B70: Гіпсокартон | C70: Монтаж відкосів з гіпсокартону на профілі | D70: м.п. | E70: 230 | F70: 230 | G70: 390 | H70: 650 | I70: підняти | J70: 380 | K70: =IF(AND(ISNUMBER(J70),E70>0),J70/E70-1,"") -> 0.65217391 | N70: =IF(L70="Своя ціна",M70,IF(L70="Прийняти",IF(ISNUMBER(J70),J70,E70),E70)) -> 230 | O70: На самому мінімумі. Варіант 'на клей' (230) — ~350. | P70: https://www.rabotniki.ua/uk/montazh-gipsokartona · Монтаж укосів з ГКЛ 230/393/650 · Україна · 2026 https://www.rabotniki.ua/uk/montazh-gipsokartona/kiev · 230/388/550 · Київ · 2026 https://www.rabotniki.ua/uk/montazh-gipsokartona/lvov · 400/417/450 · Львів · 2026 https://bud.arsel.com.ua/tsiny-na-budivelni-roboty/ · 340 · Київ · 2026-01 https://www.remonthub.org/prices.php · 350 · Київ · 2026 https://kabanchik.ua/ua/kyiv/tag/montazh-konstruktsii-z-hipsokartonu · 390 · Київ · 2026-10 https://budver.com/masters/gipsokartonni-roboti · від 253 · Київ та інші · 2026
A71: Малярка і гіпсокартон | B71: Гіпсокартон | C71: Монтаж профілю тіньового шва по периметру стелі | D71: м.п. | E71: 400 | F71: 500 | G71: 630 | H71: 800 | I71: підняти | J71: 600 | K71: =IF(AND(ISNUMBER(J71),E71>0),J71/E71-1,"") -> 0.5 | N71: =IF(L71="Своя ціна",M71,IF(L71="Прийняти",IF(ISNUMBER(J71),J71,E71),E71)) -> 400 | O71: Лише rabotniki (3 міські зрізи, мало пропозицій). | P71: https://www.rabotniki.ua/uk/montazh-gipsokartona · Профіль тіньового шва 500/624/800 · Україна · 2026 https://www.rabotniki.ua/uk/montazh-gipsokartona/kiev · 600/630/700 · Київ · 2026 https://www.rabotniki.ua/uk/montazh-gipsokartona/lvov · 550/667/750 · Львів · 2026
A72: Малярка і гіпсокартон | B72: Гіпсокартон | C72: Монтаж треків прихованого карниза | D72: м.п. | E72: 1400 | F72: 1500 | G72: 1800 | H72: 2800 | I72: підняти | J72: 1800 | K72: =IF(AND(ISNUMBER(J72),E72>0),J72/E72-1,"") -> 0.28571429 | N72: =IF(L72="Своя ціна",M72,IF(L72="Прийняти",IF(ISNUMBER(J72),J72,E72),E72)) -> 1400 | O72: Лише rabotniki; нижче мінімуму. | P72: https://www.rabotniki.ua/uk/montazh-gipsokartona · Треки і карнизи прихованого монтажу 1500/2032/2800 · Україна · 2026 https://www.rabotniki.ua/uk/montazh-gipsokartona/kiev · 1500/1800/2200 · Київ · 2026 https://www.rabotniki.ua/uk/montazh-gipsokartona/lvov · 2000 · Львів · 2026
A73: Малярка і гіпсокартон | B73: Гіпсокартон | C73: Облаштування ніші ГКЛ з підсвічуванням | D73: м.п. | E73: 400 | F73: 500 | G73: 600 | H73: 900 | I73: підняти | J73: 600 | K73: =IF(AND(ISNUMBER(J73),E73>0),J73/E73-1,"") -> 0.5 | N73: =IF(L73="Своя ціна",M73,IF(L73="Прийняти",IF(ISNUMBER(J73),J73,E73),E73)) -> 400 | O73: Також є 'Монтаж ніші під прихований карниз' 550 — схожа робота, ціни мають бути близькі. | P73: https://www.rabotniki.ua/uk/montazh-gipsokartona · Ніша в стелі з підсвічуванням 500/666/900 · Україна · 2026 https://www.rabotniki.ua/uk/montazh-gipsokartona/kiev · 350/613/730 · Київ · 2026 https://www.rabotniki.ua/uk/montazh-gipsokartona/lvov · 400/583/750 · Львів · 2026 https://kabanchik.ua/ua/kyiv/tag/montazh-konstruktsii-z-hipsokartonu · 590 · Київ · 2026-10 https://budver.com/masters/gipsokartonni-roboti · від 550 · Київ та інші · 2026 https://www.remonthub.org/prices.php · 800 · Київ · 2026
A74: Малярка і гіпсокартон | B74: Гіпсокартон | C74: Обшивка інсталяції в т.ч. отвори | D74: шт | E74: 900 | F74: 1390 | G74: 2000 | H74: 3200 | I74: підняти | J74: 2000 | K74: =IF(AND(ISNUMBER(J74),E74>0),J74/E74-1,"") -> 1.2222222 | N74: =IF(L74="Своя ціна",M74,IF(L74="Прийняти",IF(ISNUMBER(J74),J74,E74),E74)) -> 900 | O74: Одиниці різні (шт vs м²), але коробка інсталяції ~1–1,5 м², тож 900/шт явно мало. | P74: https://stroyremdizayn.kiev.ua/rascenki-na-otdelochnye-raboty.html · Обшивка інсталяції, в т.ч. отвори 2300 грн/шт · Київ · 2026 https://www.rabotniki.ua/uk/montazh-gipsokartona · Оздоблення г/к інсталяції в с/в 1390/2410/3200 грн/м² · Україна · 2026 https://budver.com/masters/gipsokartonni-roboti · від 1529 грн/м² · Київ та інші · 2026
A75: Малярка і гіпсокартон | B75: Гіпсокартон | C75: Шпаклювання та шліфування гіпсокартону (без склополотна) | D75: м² | E75: 130 | F75: 190 | G75: 250 | H75: 600 | I75: підняти | J75: 220 | K75: =IF(AND(ISNUMBER(J75),E75>0),J75/E75-1,"") -> 0.69230769 | N75: =IF(L75="Своя ціна",M75,IF(L75="Прийняти",IF(ISNUMBER(J75),J75,E75),E75)) -> 130 | O75: Якщо це повна підготовка ГКЛ під фарбування — нижче ринку. Якщо лише шви+шурупи, це дубль 'Шпаклювання швів ГКЛ' (100). | P75: https://kabanchik.ua/ua/kyiv/category/shpaklivka-stin · ГКЛ стіни під фарбування 190 · Київ · 2026-10 https://www.rabotniki.ua/uk/malyarnye-raboty/kiev · Підготовка г.к. стіни під фарбування 300/438/600 · Київ · 2026 https://budver.com/masters/shtukaturno-malyarni-roboti · від 275 · Київ та інші · 2026 https://creativebuild.com.ua/shpaklyuvannya-stin-tsina-lviv/ · ГКЛ під фарбування 200–300 (Львів) · Львів · 2025-10
A76: Малярка і гіпсокартон | B76: Маляр | C76: Венеціанська штукатурка | D76: м² | E76: 400 | F76: 440 | G76: 665 | H76: 890 | I76: підняти | J76: 650 | K76: =IF(AND(ISNUMBER(J76),E76>0),J76/E76-1,"") -> 0.625 | N76: =IF(L76="Своя ціна",M76,IF(L76="Прийняти",IF(ISNUMBER(J76),J76,E76),E76)) -> 400 | O76: Нижче мінімуму обох джерел. | P76: https://www.rabotniki.ua/uk/dekorativnaya-otdelka-sten · Венеціанська штукатурка 495/665/890 · Україна · 2026 https://budver.com/masters/shtukaturno-malyarni-roboti · Нанесення венеціанської штукатурки від 440 · Київ та інші · 2026
A77: Малярка і гіпсокартон | B77: Маляр | C77: Машинна штукатурка стель | D77: м² | E77: 300 | F77: 320 | G77: 470 | H77: 650 | I77: підняти | J77: 450 | K77: =IF(AND(ISNUMBER(J77),E77>0),J77/E77-1,"") -> 0.5 | N77: =IF(L77="Своя ціна",M77,IF(L77="Прийняти",IF(ISNUMBER(J77),J77,E77),E77)) -> 300 | O77: Нижче мінімуму в усіх джерелах. | P77: https://www.rabotniki.ua/uk/shtukaturnye-raboty · Машинна штукатурка стель 350/478/650 · Україна · 2026 https://www.rabotniki.ua/uk/shtukaturnye-raboty/kiev · 400/518/650 · Київ · 2026 https://www.rabotniki.ua/uk/shtukaturnye-raboty/lvov · 320/481/600 · Львів · 2026 https://kabanchik.ua/ua/kyiv/category/mashynna-shtukaturka · 440 грн/м² · Київ · 2026-10 https://budver.com/masters/shtukaturno-malyarni-roboti · від 385 · Київ та інші · 2026
A78: Малярка і гіпсокартон | B78: Маляр | C78: Нанесення рідких шпалер | D78: м² | E78: 180 | F78: 180 | G78: 270 | H78: 420 | I78: підняти | J78: 260 | K78: =IF(AND(ISNUMBER(J78),E78>0),J78/E78-1,"") -> 0.44444444 | N78: =IF(L78="Своя ціна",M78,IF(L78="Прийняти",IF(ISNUMBER(J78),J78,E78),E78)) -> 180 | O78: На мінімумі ринку. | P78: https://www.rabotniki.ua/uk/pokleyka-oboev · Нанесення рідких шпалер 180–420, сер. 298 · Україна · 2026 https://bud.arsel.com.ua/tsiny-na-budivelni-roboty/ · 265 · Київ · 2026-01 https://vikna.tv/styl-zhyttya/skilky-koshtuye-pokleyity-kvadratnyj-metr-shpaler-u-2026-rotsi/ · ~266–269 · Україна · 2026-09-21
A79: Малярка і гіпсокартон | B79: Маляр | C79: Шліфування штукатурки | D79: м² | E79: 50 | F79: 70 | G79: 95 | H79: 150 | I79: підняти | J79: 90 | K79: =IF(AND(ISNUMBER(J79),E79>0),J79/E79-1,"") -> 0.8 | N79: =IF(L79="Своя ціна",M79,IF(L79="Прийняти",IF(ISNUMBER(J79),J79,E79),E79)) -> 50 | O79: Нижче мінімуму всіх джерел. | P79: https://www.rabotniki.ua/uk/shtukaturnye-raboty · Шліфування штукатурки стін 70/95/140 · Україна · 2026 https://www.rabotniki.ua/uk/shtukaturnye-raboty/kiev · 70/85/100 · Київ · 2026 https://www.rabotniki.ua/uk/shtukaturnye-raboty/lvov · 70/109/150 · Львів · 2026 https://stroyremdizayn.kiev.ua/rascenki-na-otdelochnye-raboty.html · Шліфування стін після штукатурки (не нами) 100 · Київ · 2026
A80: Малярка і гіпсокартон | B80: Маляр | C80: Штукатурка Марморіно | D80: м² | E80: 500 | F80: 450 | G80: 800 | H80: 1090 | I80: підняти | J80: 750 | K80: =IF(AND(ISNUMBER(J80),E80>0),J80/E80-1,"") -> 0.5 | N80: =IF(L80="Своя ціна",M80,IF(L80="Прийняти",IF(ISNUMBER(J80),J80,E80),E80)) -> 500 | O80: Лише одне джерело з повним діапазоном (rabotniki, 60 пропозицій); друге — 'від'. Підвищувати обережно. | P80: https://www.rabotniki.ua/uk/dekorativnaya-otdelka-sten · Штукатурка Марморіно 450/802/1090 · Україна · 2026 https://budver.com/masters/shtukaturno-malyarni-roboti · Венеціанська під мармур від 440 · Київ та інші · 2026
A81: Малярка і гіпсокартон | B81: Маляр | C81: Штукатурка Марсельський віск | D81: м² | E81: 500 | F81: 500 | G81: 670 | H81: 850 | I81: підняти | J81: 650 | K81: =IF(AND(ISNUMBER(J81),E81>0),J81/E81-1,"") -> 0.3 | N81: =IF(L81="Своя ціна",M81,IF(L81="Прийняти",IF(ISNUMBER(J81),J81,E81),E81)) -> 500 | O81: На мінімумі; одне джерело з діапазоном. | P81: https://www.rabotniki.ua/uk/dekorativnaya-otdelka-sten · Марсельський віск 500/672/850 · Україна · 2026 https://budver.com/masters/shtukaturno-malyarni-roboti · декоративна від 330–440 · Київ та інші · 2026
... A89: Малярка і гіпсокартон | B89: Маляр | C89: Поклейка шпалер шириною 50 см на стіну (з підбором) | D89: м² | E89: 300 | F89: 150 | G89: 220 | H89: 350 | I89: знизити | J89: 240 | K89: =IF(AND(ISNUMBER(J89),E89>0),J89/E89-1,"") -> -0.2 | N89: =IF(L89="Своя ціна",M89,IF(L89="Прийняти",IF(ISNUMBER(J89),J89,E89),E89)) -> 300 | O89: Найдорожча з 4 позицій шпалер; ринок з підбором ~200–220. | P89: https://kabanchik.ua/ua/kyiv/category/pokleika-shpaler · флізелінові з підбором 200 · Київ · 2026-10 https://stroyremdizayn.kiev.ua/rascenki-na-otdelochnye-raboty.html · 50 см з підбором 220 · Київ · 2026 https://www.rabotniki.ua/uk/pokleyka-oboev · паперові сер. 217, макс 350 · Україна · 2026 https://bud.arsel.com.ua/tsiny-na-budivelni-roboty/ · паперові 175 · Київ · 2026-01
A90: Малярка і гіпсокартон | B90: Гіпсокартон | C90: Монтаж гіпсокартону на стіни на клей (безкаркасно) | D90: м² | E90: 280 | I90: неясно | K90: =IF(AND(ISNUMBER(J90),E90>0),J90/E90-1,"") | N90: =IF(L90="Своя ціна",M90,IF(L90="Прийняти",IF(ISNUMBER(J90),J90,E90),E90)) -> 280 | O90: Лише одне джерело (400); на rabotniki окремої позиції немає. | P90: https://www.remonthub.org/prices.php · Облицювання стін ГКЛ на клей 400 · Київ · 2026
A91: Малярка і гіпсокартон | B91: Гіпсокартон | C91: Заповнення та армування стиків ГКЛ | D91: м.п. | E91: 100 | F91: 60 | G91: 105 | H91: 150 | I91: в ринку | K91: =IF(AND(ISNUMBER(J91),E91>0),J91/E91-1,"") | N91: =IF(L91="Своя ціна",M91,IF(L91="Прийняти",IF(ISNUMBER(J91),J91,E91),E91)) -> 100 | P91: https://www.rabotniki.ua/uk/malyarnye-raboty · Закладення швів ГК 60/102/150; армування стрічкою 70/107/150 · Україна · 2026 https://www.rabotniki.ua/uk/malyarnye-raboty/kiev · 109 / 112 · Київ · 2026 https://bud.arsel.com.ua/tsiny-na-budivelni-roboty/ · армування стрічкою 85 · Київ · 2026-01 https://liv-comfort.kyiv.ua/price-remont/index.html · Заробка стиків + серпянка 100 · Київ · 2026 https://budver.com/masters/shtukaturno-malyarni-roboti · від 66 · Київ та інші · 2026
A92: Малярка і гіпсокартон | B92: Гіпсокартон | C92: Монтаж арки з гіпсокартону | D92: шт | E92: 1500 | F92: 850 | G92: 1450 | H92: 2100 | I92: в ринку | K92: =IF(AND(ISNUMBER(J92),E92>0),J92/E92-1,"") | N92: =IF(L92="Своя ціна",M92,IF(L92="Прийняти",IF(ISNUMBER(J92),J92,E92),E92)) -> 1500 | P92: https://www.rabotniki.ua/uk/montazh-gipsokartona · Декор. елементи (ніші, арки) 850/1528/2100 грн/шт · Україна · 2026 https://www.rabotniki.ua/uk/montazh-gipsokartona/kiev · 1000/1349/2000 · Київ · 2026 https://www.rabotniki.ua/uk/montazh-gipsokartona/lvov · 850/1479/2100 · Львів · 2026 https://www.remonthub.org/prices.php · Улаштування арки від 1000 · Київ · 2026 https://budver.com/masters/gipsokartonni-roboti · від 935 · Київ та інші · 2026
A93: Малярка і гіпсокартон | B93: Гіпсокартон | C93: Монтаж вертикального короба з гіпсокартону на стояки | D93: м.п. | E93: 620 | F93: 300 | G93: 500 | H93: 800 | I93: в ринку | K93: =IF(AND(ISNUMBER(J93),E93>0),J93/E93-1,"") | N93: =IF(L93="Своя ціна",M93,IF(L93="Прийняти",IF(ISNUMBER(J93),J93,E93),E93)) -> 620 | O93: Вище медіани (~500) на ~25%. | P93: https://www.rabotniki.ua/uk/montazh-gipsokartona · Обшивка труб ГКЛ 350/514/750 · Україна · 2026 https://www.rabotniki.ua/uk/montazh-gipsokartona/kiev · 300/525/800 · Київ · 2026 https://www.rabotniki.ua/uk/montazh-gipsokartona/lvov · 300/450/550 · Львів · 2026 https://bud.arsel.com.ua/tsiny-na-budivelni-roboty/ · 485 · Київ · 2026-01 https://www.remonthub.org/prices.php · Зашивка труб 300; Г-подібний 800 · Київ · 2026 https://budver.com/masters/gipsokartonni-roboti · від 396 · Київ та інші · 2026
A94: Малярка і гіпсокартон | B94: Гіпсокартон | C94: Монтаж гіпсокартону на стелю рівну | D94: м² | E94: 560 | F94: 300 | G94: 520 | H94: 750 | I94: в ринку | K94: =IF(AND(ISNUMBER(J94),E94>0),J94/E94-1,"") | N94: =IF(L94="Своя ціна",M94,IF(L94="Прийняти",IF(ISNUMBER(J94),J94,E94),E94)) -> 560 | P94: https://www.rabotniki.ua/uk/montazh-gipsokartona · на стелю 300/521/700 · Україна · 2026 https://www.rabotniki.ua/uk/montazh-gipsokartona/kiev · 300/490/700 · Київ · 2026 https://www.rabotniki.ua/uk/montazh-gipsokartona/lvov · 400/538/750 · Львів · 2026 https://bud.arsel.com.ua/tsiny-na-budivelni-roboty/ · 435 · Київ · 2026-01 https://www.remonthub.org/prices.php · однорівнева 600 · Київ · 2026 https://kabanchik.ua/ua/kyiv/tag/montazh-konstruktsii-z-hipsokartonu · 480 · Київ · 2026-10 https://budver.com/masters/gipsokartonni-roboti · від 352 · Київ та інші · 2026
A95: Малярка і гіпсокартон | B95: Гіпсокартон | C95: Монтаж гіпсокартону на стіни | D95: м² | E95: 430 | F95: 250 | G95: 410 | H95: 650 | I95: в ринку | K95: =IF(AND(ISNUMBER(J95),E95>0),J95/E95-1,"") | N95: =IF(L95="Своя ціна",M95,IF(L95="Прийняти",IF(ISNUMBER(J95),J95,E95),E95)) -> 430 | P95: https://www.rabotniki.ua/uk/montazh-gipsokartona · на стіну 250/417/650 · Україна · 2026 https://www.rabotniki.ua/uk/montazh-gipsokartona/kiev · 250/402/600 · Київ · 2026 https://www.rabotniki.ua/uk/montazh-gipsokartona/lvov · 300/390/450 · Львів · 2026 https://bud.arsel.com.ua/tsiny-na-budivelni-roboty/ · 355 · Київ · 2026-01 https://www.remonthub.org/prices.php · пристінна конструкція 450 · Київ · 2026 https://kabanchik.ua/ua/kyiv/tag/montazh-konstruktsii-z-hipsokartonu · 420 · Київ · 2026-10 https://budver.com/masters/gipsokartonni-roboti · від 275 · Київ та інші · 2026
A96: Малярка і гіпсокартон | B96: Гіпсокартон | C96: Монтаж короба (прямого) із гіпсокартону по периметру стелі | D96: м.п. | E96: 550 | F96: 300 | G96: 510 | H96: 800 | I96: в ринку | K96: =IF(AND(ISNUMBER(J96),E96>0),J96/E96-1,"") | N96: =IF(L96="Своя ціна",M96,IF(L96="Прийняти",IF(ISNUMBER(J96),J96,E96),E96)) -> 550 | P96: https://www.rabotniki.ua/uk/montazh-gipsokartona · Короб по периметру 300/513/750 · Україна · 2026 https://www.rabotniki.ua/uk/montazh-gipsokartona/kiev · 400/545/800 · Київ · 2026 https://www.rabotniki.ua/uk/montazh-gipsokartona/lvov · 500/583/750 · Львів · 2026 https://kabanchik.ua/ua/kyiv/tag/montazh-konstruktsii-z-hipsokartonu · 410 · Київ · 2026-10 https://budver.com/masters/gipsokartonni-roboti · від 330 · Київ та інші · 2026
A97: Малярка і гіпсокартон | B97: Гіпсокартон | C97: Утеплення мінватою в один шар | D97: м² | E97: 160 | F97: 120 | G97: 200 | H97: 300 | I97: в ринку | K97: =IF(AND(ISNUMBER(J97),E97>0),J97/E97-1,"") | N97: =IF(L97="Своя ціна",M97,IF(L97="Прийняти",IF(ISNUMBER(J97),J97,E97),E97)) -> 160 | P97: https://www.rabotniki.ua/uk/montazh-gipsokartona · Утеплення мінватою 130/216/300 · Україна · 2026 https://www.rabotniki.ua/uk/montazh-gipsokartona/kiev · 120/200/300 · Київ · 2026 https://bud.arsel.com.ua/tsiny-na-budivelni-roboty/ · 130 · Київ · 2026-01 https://budver.com/masters/gipsokartonni-roboti · від 143 · Київ та інші · 2026
A98: Малярка і гіпсокартон | B98: Маляр | C98: Грунтовка поверхонь бетоноконтактом | D98: м² | E98: 100 | F98: 60 | G98: 90 | H98: 123 | I98: в ринку | K98: =IF(AND(ISNUMBER(J98),E98>0),J98/E98-1,"") | N98: =IF(L98="Своя ціна",M98,IF(L98="Прийняти",IF(ISNUMBER(J98),J98,E98),E98)) -> 100 | P98: https://www.rabotniki.ua/uk/shtukaturnye-raboty · Грунтовка бетоноконтактом 60/88/123 · Україна · 2026 https://www.rabotniki.ua/uk/shtukaturnye-raboty/kiev · 60/92/123 · Київ · 2026 https://www.rabotniki.ua/uk/shtukaturnye-raboty/lvov · 75/77/80 · Львів · 2026 https://bud.arsel.com.ua/tsiny-na-budivelni-roboty/ · 75 · Київ · 2026-01 https://liv-comfort.kyiv.ua/price-remont/index.html · 100 · Київ · 2026 https://budver.com/masters/shtukaturno-malyarni-roboti · від 66 · Київ та інші · 2026
A99: Малярка і гіпсокартон | B99: Маляр | C99: Грунтування | D99: м² | E99: 33 | F99: 25 | G99: 40 | H99: 55 | I99: в ринку | J99: 40 | K99: =IF(AND(ISNUMBER(J99),E99>0),J99/E99-1,"") -> 0.21212121 | N99: =IF(L99="Своя ціна",M99,IF(L99="Прийняти",IF(ISNUMBER(J99),J99,E99),E99)) -> 33 | O99: На нижній межі; медіана ~40. Є ще 'Грунтування перед шпаклівкою' 50 і 'Грунтування основи перед штукатуркою' 35 — по суті одна робота за трьома цінами. | P99: https://www.rabotniki.ua/uk/malyarnye-raboty · Грунтовка стін, стелі (1 шар) 25/40/55 · Україна · 2026 https://www.rabotniki.ua/uk/malyarnye-raboty/kiev · 35/43/55 · Київ · 2026 https://bud.arsel.com.ua/tsiny-na-budivelni-roboty/ · 35 · Київ · 2026-01 https://www.remonthub.org/prices.php · 35 · Київ · 2026 https://kabanchik.ua/ua/kyiv/category/pokleika-shpaler · Грунтовка стін 39 / стелі 44 · Київ · 2026-10 https://budver.com/masters/shtukaturno-malyarni-roboti · від 27 · Київ та інші · 2026
A100: Малярка і гіпсокартон | B100: Маляр | C100: Нанесення декоративної штукатурки "ефект бетону", "арт бетон" | D100: м² | E100: 750 | F100: 400 | G100: 570 | H100: 790 | I100: в ринку | K100: =IF(AND(ISNUMBER(J100),E100>0),J100/E100-1,"") | N100: =IF(L100="Своя ціна",M100,IF(L100="Прийняти",IF(ISNUMBER(J100),J100,E100),E100)) -> 750 | O100: Біля верхньої межі. | P100: https://www.rabotniki.ua/uk/dekorativnaya-otdelka-sten · Ефект бетону 400/593/790 · Україна · 2026 https://stroyremdizayn.kiev.ua/rascenki-na-otdelochnye-raboty.html · ефект бетону 550 · Київ · 2026
A101: Малярка і гіпсокартон | B101: Маляр | C101: Нанесення декоративної штукатурки "мармурова крихта" | D101: м² | E101: 500 | F101: 400 | G101: 510 | H101: 700 | I101: в ринку | K101: =IF(AND(ISNUMBER(J101),E101>0),J101/E101-1,"") | N101: =IF(L101="Своя ціна",M101,IF(L101="Прийняти",IF(ISNUMBER(J101),J101,E101),E101)) -> 500 | P101: https://www.rabotniki.ua/uk/dekorativnaya-otdelka-sten · Мармурова крихта 400/512/700 · Україна · 2026 https://stroyremdizayn.kiev.ua/rascenki-na-otdelochnye-raboty.html · від 400 · Київ · 2026
A102: Малярка і гіпсокартон | B102: Маляр | C102: Нанесення декоративної штукатурки "травертин" | D102: м² | E102: 750 | F102: 400 | G102: 570 | H102: 790 | I102: в ринку | K102: =IF(AND(ISNUMBER(J102),E102>0),J102/E102-1,"") | N102: =IF(L102="Своя ціна",M102,IF(L102="Прийняти",IF(ISNUMBER(J102),J102,E102),E102)) -> 750 | O102: Біля верхньої межі; медіана ~570. | P102: https://www.rabotniki.ua/uk/dekorativnaya-otdelka-sten · Травертин 400/591/790 · Україна · 2026 https://stroyremdizayn.kiev.ua/rascenki-na-otdelochnye-raboty.html · травертин 550 · Київ · 2026
A103: Малярка і гіпсокартон | B103: Маляр | C103: Поклейка склополотна | D103: м² | E103: 160 | F103: 110 | G103: 170 | H103: 240 | I103: в ринку | K103: =IF(AND(ISNUMBER(J103),E103>0),J103/E103-1,"") | N103: =IF(L103="Своя ціна",M103,IF(L103="Прийняти",IF(ISNUMBER(J103),J103,E103),E103)) -> 160 | O103: Дубль у DRYWALL з тією ж ціною. | P103: https://www.rabotniki.ua/uk/malyarnye-raboty · Наклейка скловолокна 110/170/240 · Україна · 2026 https://www.rabotniki.ua/uk/malyarnye-raboty/kiev · 120/181/220 · Київ · 2026 https://bud.arsel.com.ua/tsiny-na-budivelni-roboty/ · Наклейка склополотна 130 · Київ · 2026-01 https://www.remonthub.org/prices.php · 190 · Київ · 2026 https://kabanchik.ua/ua/kyiv/category/pokleika-shpaler · на стелю 180 · Київ · 2026-10 https://budver.com/masters/shtukaturno-malyarni-roboti · від 121 · Київ та інші · 2026
A104: Малярка і гіпсокартон | B104: Маляр | C104: Поклейка склошпалер (структурних) під фарбування | D104: м² | E104: 190 | F104: 140 | G104: 190 | H104: 250 | I104: в ринку | K104: =IF(AND(ISNUMBER(J104),E104>0),J104/E104-1,"") | N104: =IF(L104="Своя ціна",M104,IF(L104="Прийняти",IF(ISNUMBER(J104),J104,E104),E104)) -> 190 | P104: https://www.rabotniki.ua/uk/pokleyka-oboev · Скловолокнисті на стіни 140–250, сер. 196 · Україна · 2026 https://bud.arsel.com.ua/tsiny-na-budivelni-roboty/ · склошпалери на стіни 150 · Київ · 2026-01 https://vikna.tv/styl-zhyttya/skilky-koshtuye-pokleyity-kvadratnyj-metr-shpaler-u-2026-rotsi/ · ~187 · Україна · 2026-09-21
A105: Малярка і гіпсокартон | B105: Маляр | C105: Поклейка фотошпалер | D105: м² | E105: 450 | F105: 230 | G105: 390 | H105: 650 | I105: в ринку | K105: =IF(AND(ISNUMBER(J105),E105>0),J105/E105-1,"") | N105: =IF(L105="Своя ціна",M105,IF(L105="Прийняти",IF(ISNUMBER(J105),J105,E105),E105)) -> 450 | O105: Вище медіани, але в межах. Можна ~400. | P105: https://www.rabotniki.ua/uk/pokleyka-oboev · Фотошпалери 230–650, сер. 399 · Україна · 2026 https://bud.arsel.com.ua/tsiny-na-budivelni-roboty/ · 305 · Київ · 2026-01 https://liv-comfort.kyiv.ua/price-remont/index.html · 250 · Київ · 2026 https://vikna.tv/styl-zhyttya/skilky-koshtuye-pokleyity-kvadratnyj-metr-shpaler-u-2026-rotsi/ · ~389 · Україна · 2026-09-21
A106: Малярка і гіпсокартон | B106: Маляр | C106: Фарбування безповітряним методом (airless) | D106: м² | E106: 180 | F106: 130 | G106: 210 | H106: 280 | I106: в ринку | K106: =IF(AND(ISNUMBER(J106),E106>0),J106/E106-1,"") | N106: =IF(L106="Своя ціна",M106,IF(L106="Прийняти",IF(ISNUMBER(J106),J106,E106),E106)) -> 180 | O106: Нижче мінімуму Києва (195); для Києва краще ~210. | P106: https://www.rabotniki.ua/uk/malyarnye-raboty · Безповітряне фарбування 130/211/250 · Україна · 2026 https://www.rabotniki.ua/uk/malyarnye-raboty/kiev · 195/225/250 · Київ · 2026 https://www.rabotniki.ua/uk/malyarnye-raboty/lvov · 170/200/280 · Львів · 2026 https://budver.com/masters/shtukaturno-malyarni-roboti · від 143 · Київ та інші · 2026
A107: Малярка і гіпсокартон | B107: Маляр | C107: Фарбування стелі водоемульсійною фарбою | D107: м² | E107: 220 | F107: 135 | G107: 205 | H107: 330 | I107: в ринку | K107: =IF(AND(ISNUMBER(J107),E107>0),J107/E107-1,"") | N107: =IF(L107="Своя ціна",M107,IF(L107="Прийняти",IF(ISNUMBER(J107),J107,E107),E107)) -> 220 | P107: https://www.rabotniki.ua/uk/malyarnye-raboty · 135/209/330 · Україна · 2026 https://www.rabotniki.ua/uk/malyarnye-raboty/kiev · 135/221/330 · Київ · 2026 https://www.rabotniki.ua/uk/malyarnye-raboty/lvov · 150/173/180 · Львів · 2026 https://bud.arsel.com.ua/tsiny-na-budivelni-roboty/ · 175 · Київ · 2026-01 https://kabanchik.ua/ua/kyiv/category/pokleika-shpaler · Фарбування стелі валиком 140 · Київ · 2026-10 https://budver.com/masters/shtukaturno-malyarni-roboti · від 148 · Київ та інші · 2026
...

Sheet Аномалії
A1: Група | B1: Фах | C1: Позиція | D1: Од. | E1: Наша ціна, ₴ | F1: Що не так | G1: Пропонована ціна, ₴ | H1: Рішення | I1: Коментар
A2: Плитка і підлоги | B2: Плитка | C2: Затирання швів у декоративній плитці, мозаїці | D2: м² | E2: 0 | F2: Ціна 0. Ринок: PK — затирка 180 + доплата за мозаїку 120 = 300 грн/м²; remmo — мозаїка 130 грн/м²; сусідня цементна затирка 116. | G2: 300
A3: Плитка і підлоги | B3: Плитка | C3: Укладання декоративної плитки під «цеглу» або «камінь» (гіпсова, бетонна) | D3: м² | E3: 0 | F3: Ціна 0 (див. checked: ринок ~1000–1100 грн/м²). | G3: 1000
A4: Плитка і підлоги | B4: Плитка | C4: Облицювання плиткою короба | D4: м² | E4: 0 | F4: Ціна 0 і, ймовірно, неправильна одиниця: ринок рахує в м.п. (rabotniki 600/993/1500 грн/м.п.; budver від 660 грн/м.п.). | G4: 900
A5: Плитка і підлоги | B5: Плитка | C5: Гідроізоляція плівкова | D5: м² | E5: 0 | F5: Ціна 0. Ринок 60–64 грн/м² (rabotniki, arsel, stroyremdizayn). | G5: 60
A6: Плитка і підлоги | B6: Плитка | C6: Гідроізоляція сухою сумішшю | D6: м² | E6: 0 | F6: Ціна 0. stroyremdizayn 130 грн/м²; PK цементна 2 шари 264 грн/м²; сусідня мастика 174. | G6: 200
A7: Плитка і підлоги | B7: Плитка | C7: Поклейка гідроізоляційних муфт на водорозетки | D7: шт | E7: 0 | F7: Ціна 0. PK 360 грн/шт; сусідня позиція 'гідроізоляційні кути' 100 грн/шт. | G7: 250
A8: Плитка і підлоги | B8: Плитка | C8: Монтаж трапу та формування ухилу до нього | D8: шт | E8: 0 | F8: Ціна 0 для однієї з ключових позицій ванної. Публічних цін не знайшов; потрібне значення.
A9: Плитка і підлоги | B9: Плитка | C9: Монтаж лінійного душового каналу | D9: шт | E9: 0 | F9: Ціна 0 для ключової позиції. Потрібне значення (зазвичай дорожче за точковий трап).
A10: Плитка і підлоги | B10: Плитка | C10: Влаштування деформаційних швів | D10: м.п. | E10: 0 | F10: Ціна 0. PK: джгут 60 + герметизація 240 грн/м.п.
A11: Плитка і підлоги | B11: Плитка | C11: Укладання плитки поверх теплої підлоги (плюс % до м.кв.) | D11: % | E11: 0 | F11: 0%. Тоді позиція нічого не додає: або видалити, або дати ненульову доплату.
A12: Плитка і підлоги | B12: Плитка | C12: Укладання плитки ялинкою (плюс % до м.кв.) | D12: % | E12: 0 | F12: 0%. PK: діагональ/ялинка від +15%; duflu: ялинка/діагональ у Києві 1100–1800 проти 800–1400 за пряму укладку (≈+30%). Сусідня діагональ +33%. | G12: 30
A13: Плитка і підлоги | B13: Плитка | C13: Укладання плитки на шар клею більше 1 см | D13: м² | E13: 0 | F13: Ціна 0 і одиниця M2 для того, що за змістом є доплатою. stroyremdizayn: +150 грн/м² за товщину понад 1 см; PK: вирівнювання клеєм до 10 мм 264 грн/м². | G13: 150
A14: Плитка і підлоги | B14: Плитка | C14: Винесення та вивезення будівельного сміття | D14: м³ | E14: 0 | F14: TILING 0, а такий самий рядок у FLOORING — 600 грн/м³. | G14: 600
A15: Плитка і підлоги | B15: Плитка | C15: Прибирання приміщення після робіт | D15: м² | E15: 0 | F15: TILING 0, а такий самий рядок у FLOORING — 40 грн/м². | G15: 40
A16: Плитка і підлоги | B16: Плитка | C16: Укриття плівкою підлоги, дверей, сантехніки | D16: м² | E16: 0 | F16: Ціна 0. Сусідні позиції: картон 30, ДВП 70 грн/м². | G16: 30
A17: Плитка і підлоги | B17: Плитка | C17: Виготовлення та монтаж кріплення для раковини (зварювання, фарбування) | D17: шт | E17: 0 | F17: Ціна 0.
A18: Плитка і підлоги | B18: Плитка | C18: Підняття матеріалу по сходах | D18: т | E18: 1642 | F18: Ціна 1642 за тонну не залежить від поверху, хоча сусідній рядок рахується за поверх (FLOOR). Ринок: вантажники ~10–25 ₴ за мішок за поверх.
A19: Плитка і підлоги | B19: Плитка | C19: Розвантаження матеріалу | D19: т | E19: 1271 | F19: PK: 750 ₴/т, наші 1271 ₴/т — помітно вище ринку.
A20: Плитка і підлоги | B20: Плитка | C20: Формування кута з епоксидної суміші | D20: м² | E20: 287 | F20: Одиниця M2 для лінійного елемента. PK: епоксидний зовнішній кут 360 грн/м.п.; plitka.ua: кут епоксидом 300 грн/м.п. Треба LINEAR_METER. | G20: 320
A21: Плитка і підлоги | B21: Плитка | C21: Заміна силіконового шва (видалення старого, нанесення нового) | D21: м.п. | E21: 180 | F21: 180 грн/м.п. — близько до простого заповнення (130), а за ринком (rabotniki 215, PK 240) і нижче за нього. Заміна з видаленням має бути дорожчою. | G21: 280
A22: Плитка і підлоги | B22: Плитка | C22: Сортування плитки та підбір малюнка | D22: м² | E22: 247 | F22: 247 грн/м² завищено: PK — підбір малюнка 60 грн/м² (сортування окремо, 360 грн/год); plitka.ua — підбір малюнка 80 грн/м². | G22: 100
A23: Плитка і підлоги | B23: Плитка | C23: Стяжка маякова цементна | D23: м² | E23: 342 | F23: Різниться з FLOORING 'Цементно-піщана стяжка понад 20м2' (400) / 'до 20м2' (500) за ту саму роботу. | G23: 400
A24: Плитка і підлоги | B24: Плитка | C24: Шліфування стяжки (зняття перепадів до 5 мм) | D24: м² | E24: 392 | F24: 392 проти 150 у FLOORING 'Шліфування бетонної основи' і 161 у 'Шліфування видалення слабкого шару'. Ринок ~226. | G24: 230
A25: Плитка і підлоги | B25: Підлоги | C25: Монтаж демпферної стрічки | D25: м² | E25: 50 | F25: Одиниця M2 для стрічки: має бути LINEAR_METER (або прибрати, бо PK і mirafloor включають стрічку в ціну наливної).
A26: Плитка і підлоги | B26: Підлоги | C26: Приклеювання стиків в місцях порожків, герметизація силіконом | D26: шт | E26: 500 | F26: Дубль позиції 'Приклеювання стиків порожків герметизація' (Плінтус, 212 грн/м.п.), але з одиницею PIECE і ціною 500.
A27: Плитка і підлоги | B27: Підлоги | C27: Монтаж утеплювача під стяжку | D27: м² | E27: 302 | F27: 302 проти 130 у сусідньому 'Монтаж утеплювача'; ринок 130–200. | G27: 160
A28: Плитка і підлоги | B28: Підлоги | C28: Плівкова ізоляція під стяжку | D28: м² | E28: 134 | F28: 134 грн/м² — вдвічі вище за ринок (60–64) і за 'пароізоляційну плівку під ламінат' (30). | G28: 60
A29: Плитка і підлоги | B29: Підлоги | C29: Настил лінолеуму ковроліну на клей | D29: м² | E29: 200 | F29: Дорівнює варіанту без клею (200); на клей має бути дорожче (stroyremdizayn 300, arsel 220). | G29: 260
A30: Плитка і підлоги | B30: Підлоги | C30: Демонтаж лінолеуму ковроліну | D30: м² | E30: 20 | F30: 20 грн/м² — нереально низько (rbk-alba 250, kabanchik 130). | G30: 100
A31: Плитка і підлоги | B31: Підлоги | C31: Демонтаж плінтуса | D31: м.п. | E31: 30 | F31: 30 грн/м.п. — низько: rbk-alba 60 грн/м.п. (дерев'яний/пластиковий). | G31: 60
A32: Плитка і підлоги | B32: Підлоги | C32: Монтаж міжкімнатного порога | D32: м.п. | E32: 400 | F32: 400 грн/м.п. — удвічі більше за перехідний профіль (200); ринок ~210. Поріг зазвичай рахують за шт. | G32: 210
A33: Плитка і підлоги | B33: Плитка | C33: Укладання плитки на відкос (плюс % до м.кв.) | D33: % | E33: 88 | F33: +88% вище за ринкові доплати: plitka.ua +60%; PK — відкос до 600 мм ×0.8 від ціни м² за м.п.; rabotniki — 834 грн/м.п. Варто перевірити. | G33: 60
A34: Малярка і гіпсокартон | B34: Маляр | C34: Штукатурка стін до 2см об'ємом до 50м2 | D34: м² | E34: 280 | F34: Надбавка за малий обсяг має робити ціну вищою за звичайну ручну (330), а тут нижче. Обидві товщини мають однакову ціну 280. Джерело-аналог (stroyremdizayn): 400 (до 2 см) і 430 (від 2 см). | G34: 400
A35: Малярка і гіпсокартон | B35: Маляр | C35: Штукатурка стін від 2см об'ємом до 50м2 | D35: м² | E35: 280 | F35: Те саме: нижче за звичайну ручну від 2 см (380) і дорівнює ціні до 2 см. | G35: 430
A36: Малярка і гіпсокартон | B36: Маляр | C36: Шпаклювання стелі | D36: м² | E36: 270 | F36: Неоднозначна позиція поруч із 'Шпаклівка стелі під фарбування' (420) і 'під склополотно' (360). Якщо це повна підготовка, ціна нижче ринку (kabanchik 350, rabotniki Київ 530). Уточнити обсяг робіт або прибрати дубль.
A37: Малярка і гіпсокартон | B37: Маляр | C37: Акрилення примикань | D37: м.п. | E37: 100 | F37: Та сама робота, що й 'Герметизація швів, стиків акрилом, спеціальною мастикою' (220), але ціни різняться вдвічі. Ринок (rabotniki): герметизація акрилом 80/143/200. | G37: 140
A38: Малярка і гіпсокартон | B38: Маляр | C38: Герметизація швів, стиків акрилом, спеціальною мастикою | D38: м.п. | E38: 220 | F38: Дубль 'Акрилення примикань' (100) з іншою ціною; вище максимуму rabotniki (200). | G38: 140
A39: Малярка і гіпсокартон | B39: Маляр | C39: Відведення лінії фарби довкола вікон/дверей | D39: м² | E39: 100 | F39: Імовірно, неправильна одиниця: лінію рахують у м.п. (пор. 'Розділення кольорів (скотч)' 85 грн/м.п.).
A40: Малярка і гіпсокартон | B40: Маляр | C40: Фарбування нашовної планки | D40: м.п. | E40: 260 | F40: Дорожче за фарбування 1 м² вагонки (220) і вдвічі дорожче за монтаж цієї ж планки (120). Схоже на помилку. | G40: 80
A41: Малярка і гіпсокартон | B41: Маляр | C41: Обшивка стелі шалівкою | D41: м² | E41: 80 | F41: Шалівка — те саме, що вагонка, але вагонка на стелю коштує 550, тобто в 7 разів дорожче. rabotniki: OSB/фанера на стелю 200/320/400. | G41: 450
A42: Малярка і гіпсокартон | B42: Маляр | C42: Стелі Грильято | D42: м² | E42: 80 | F42: Абсурдно низько. rabotniki: Грильято 250/365/530. | G42: 350
A43: Малярка і гіпсокартон | B43: Маляр | C43: Підвісна стеля Армстронг | D43: м² | E43: 170 | F43: Нижче мінімуму. rabotniki 200/334/450; remonthub від 180. | G43: 300
A44: Малярка і гіпсокартон | B44: Маляр | C44: Натяжна стеля | D44: м² | E44: 340 | F44: Нижче мінімуму rabotniki (380/632/900). Ринкові ціни на натяжні стелі часто включають полотно, тому розрив може бути менший. До того ж це не малярна робота.
A45: Малярка і гіпсокартон | B45: Маляр | C45: Монтаж на стелю пластикової вагонки | D45: м² | E45: 80 | F45: Дуже дешево порівняно з дерев'яною вагонкою на стелю (550) і обрешіткою (150).
A46: Малярка і гіпсокартон | B46: Маляр | C46: Зняття шпалер | D46: м² | E46: 30 | F46: Нижче ринку: kabanchik 59 (стіни) / 63 (стеля), rbk-alba 100. Тільки vikna.tv дає 'від 10'. | G46: 60
A47: Малярка і гіпсокартон | B47: Маляр | C47: Змивання побілки зі стелі | D47: м² | E47: 60 | F47: kabanchik: змивка побілки зі стелі 110; rbk-alba: змивання вапна/крейди/водоемульсійки 110. | G47: 100
A48: Малярка і гіпсокартон | B48: Гіпсокартон | C48: Демонтаж перегородки з гіпсокартону | D48: м² | E48: 60 | F48: Нижче ринку: rbk-alba 300, budver від 165, bud.arsel 130 (демонтаж стін з ГК). | G48: 150
A49: Малярка і гіпсокартон | B49: Гіпсокартон | C49: Демонтаж гіпсокартонної стелі | D49: м² | E49: 60 | F49: rbk-alba: демонтаж ГК стелі 200; budver: демонтаж ГКЛ від 165. | G49: 150
A50: Малярка і гіпсокартон | B50: Гіпсокартон | C50: Монтаж напівкруглої конструкції ГКЛ | D50: м² | E50: 450 | F50: Дешевше за пряму перегородку (800) і радіусні перегородки (900/1000). rabotniki: напівкругла конструкція (стіни) 500/785/1000, Київ сер. 705. | G50: 700
A51: Малярка і гіпсокартон | B51: Гіпсокартон | C51: Монтаж відкосів з гіпсокартону на клей | D51: м.п. | E51: 230 | F51: Дорівнює варіанту на профілях і на мінімумі ринку (rabotniki 230/393/650; remonthub 350). | G51: 350
A52: Малярка і гіпсокартон | B52: Маляр | C52: Утеплення укосів пінопластом | D52: м.п. | E52: 600 | F52: Удвічі дорожче за утеплення укосів ватою (300), хоча на фасаді вата дорожча (500 проти 300 за пінопласт). Схоже, ціни переплутано. | G52: 300
A53: Малярка і гіпсокартон | B53: Маляр | C53: Шпаклювання стін (старт, за потреби) / Вирівнювання стін стартовою шпаклівкою по площині / Шпаклівка старт по цементній штукатурці | D53: м² | E53: 150 | F53: Три майже однакові позиції стартової шпаклівки: 150, 170 і 200. Варто об'єднати або чітко розвести за обсягом робіт.
A54: Малярка і гіпсокартон | B54: Маляр | C54: Грунтування / Грунтування перед шпаклівкою / Грунтування основи перед штукатуркою | D54: м² | E54: 33 | F54: Три ціни (33 / 50 / 35) за ту саму роботу (1 шар). Ринкова медіана ~40. | G54: 40
A55: Малярка і гіпсокартон | B55: Гіпсокартон | C55: Монтаж пароізоляційної мембрани | D55: м² | E55: 100 | F55: У PAINTER 'Монтаж пароізоляційної або гідроізоляційної мембрани' коштує 200, тобто та сама робота має дві ціни в різних ремеслах.
A56: Малярка і гіпсокартон | B56: Маляр | C56: Організаційні послуги (11 позицій з ціною 0) | E56: 0 | F56: Нулі навмисні («договірна»), це не помилка. Зверніть увагу: у DRYWALL ті самі послуги мають ціну (вивезення сміття 600 грн/м³, прибирання 40 грн/м²).
A57: Електрика | B57: Електрика | C57: Прокладка кабелю в металорукаві | D57: м.п. | E57: 210 | F57: Удвічі-втричі дорожче за кабель у гофрі (65) і за ринок: гофра/ПВХ/металева труба 60 (РБК), гофротруба 61–83 (rabotniki), металорукав 65–75 (stroyremdizayn). Ціна 210 повторює помилкову «Прокладку кабелю». | G57: 90
A58: Електрика | B58: Електрика | C58: Отвір для розподільчої коробки в гіпсокартоні | D58: шт | E58: 200 | F58: Стоїть стільки ж, скільки отвір у бетоні. Ринок за отвір разом із коробкою в ГКЛ: 125–220 (rabotniki 141/153, arsel 125, kabanchik 220). Отвір під підрозетник у ГКЛ у нас 90. | G58: 100
A59: Електрика | B59: Електрика | C59: Монтаж розподільчої коробки в стіну | D59: шт | E59: 120 | F59: Разом з отвором (200) виходить 320 грн, а ринок за отвір і коробку дає 190 (цегла) і 250 (бетон). Посадка коробки в готовий отвір не має коштувати вдвічі більше, ніж підрозетник (60). | G59: 80
A60: Електрика | B60: Електрика | C60: Монтаж розподільчої коробки на стелю | D60: шт | E60: 120 | F60: Те саме, що й для стіни. Стеля дорожча через висоту, але сума з отвором однаково завищена. | G60: 90
A61: Електрика | B61: Електрика | C61: Комутація в підрозетнику | D61: шт | E61: 400 | F61: Дорожче за повну збірку розподільчої коробки з розпаюванням (380, ринок ~365). Якщо це з’єднання транзитних ліній у глибокому підрозетнику, ринкова логіка дає ~150–250. Варто уточнити зміст позиції.
A62: Електрика | B62: Електрика | C62: Прокладка закладної гофри в штробі для теплої підлоги | D62: м.п. | E62: 210 | F62: Учетверо дорожче за «Прокладку закладної гофри» (50) і кабель у гофрі (65). Якщо штроблення не входить, ціна має бути ~60; якщо входить, назва має про це казати. | G62: 60
A63: Електрика | B63: Електрика | C63: Установка АВР | D63: шт | E63: 400 | F63: Плутанина з «Підключенням АВР (автоввід резерву)» за 4000: та сама назва, ціни відрізняються вдесятеро. Схоже, тут мається на увазі модульний перемикач у щиті. Варто перейменувати (напр., «Установка модуля АВР/перемикача на DIN-рейку»).
A64: Електрика | B64: Електрика | C64: Установка автомата перекидного чотириполюсного | D64: шт | E64: 700 | F64: Ampérage (Львів): перемикач аварійного живлення 4-полюсний 1200, 2-полюсний 600. Наш двополюсний 600 збігається, а чотириполюсний занижений. | G64: 1000
A65: Електрика | B65: Електрика | C65: Установка реле перекидного чотириполюсного | D65: шт | E65: 400 | F65: Майже дублює «Автомат перекидний чотириполюсний» (700) і «Рубильник реверсивний» (400), але ціни різні. Чотириполюсний перемикач у щиті коштує ~1000–1200 (Ampérage).
A66: Електрика | B66: Електрика | C66: Установка контактора 380В | D66: шт | E66: 400 | F66: Стоїть стільки ж, скільки контактор 220 В. stroyremdizayn: 220 В — 440, 380 В — 600. Трифазний контактор складніший у підключенні. | G66: 550
A67: Електрика | B67: Електрика | C67: Монтаж та підключення ДБЖ | D67: точка | E67: 8000 | F67: Одиниця POINT не підходить: ДБЖ ставлять поштучно (rabotniki пише «точка», але по суті це комплект). Ціна теж низька (ринок 8000–16570, середня ~12500). | G67: 10000
A68: Електрика | B68: Електрика | C68: Установка та підключення дверного дзвінка бездротового | D68: шт | E68: 500 | F68: Бездротовий дзвінок не потребує проводки, а коштує майже як дротовий (600). Kabanchik: бездротовий від 300. | G68: 300
A69: Електрика | B69: Електрика | C69: Установка маршрутизатора комутатора | D69: шт | E69: 738 | F69: Нецілу ціну схоже перераховано (як і 147, 84, 88 в інших рядках). До того ж вона не узгоджується з «Налаштуванням Wi-Fi роутера» (200). Ampérage бере за налаштування роутера від 1500. Варто округлити й узгодити. | G69: 700
A70: Електрика | B70: Електрика | C70: Штроблення під прихований (вбудований) кабель-канал | D70: м.п. | E70: 100 | F70: Дешевше за штробу 20х20 у цеглі (130) і в бетоні (220), хоча канал ширший. Матеріал не вказано.
A71: Електрика | B71: Електрика | C71: Свердління отвору під прокладку електрокабелю в капітальній стіні - від | D71: шт | E71: 450 | F71: Частково дублює «Свердління наскрізних отворів (у бетоні) – від» за 160. Різниця виправдана хіба що товщиною стіни (санич: несуча стіна 400, зовнішня 550). Варто додати це в назву (напр., «стіна понад 30 см»).
A72: Електрика | B72: Електрика | C72: Перевірка спрацювання ПЗВ та вимірювання опору петлі фаза-нуль | D72: шт | E72: 200 | F72: Порівняно з «Вимірюванням опору заземлювального пристрою» за 1250 співвідношення ціни 1:6 дивне: обидва заміри роблять тим самим приладом. Ринкових даних від майстрів немає.
A73: Сантехніка | B73: Сантехніка | C73: Монтаж котельної котел бойлер насоси крани фільтра | D73: компл. | E73: 825 | F73: Дублікат позиції «Монтаж котельної (котел, бойлер, насоси, крани, фільтра) - від» (20000), але з абсурдною ціною 825. На ринку обв'язка котельні до 40 кВт під ключ коштує 35–80 тис. (rabotniki). Позицію треба видалити.
A74: Сантехніка | B74: Сантехніка | C74: Монтаж насоса свердловини труби трос оголовок | D74: компл. | E74: 825 | F74: Абсурдно низько: поруч стоять «Підключення свердловинного насоса» 3000 і «Монтаж обладнання свердловини» 8500. На ринку глибинний насос до 40 м з облаштуванням коштує 5500/7820/10000 (rabotniki, водопостачання). | G74: 7500
A75: Сантехніка | B75: Сантехніка | C75: Установка душової кабіни бокс | D75: шт | E75: 2000 | F75: Інверсія: бокс (гідробокс) у нас дешевший за просту кабіну (3000), хоча він складніший. На ринку кабіна коштує 3800–4000 (rabotniki, середнє); rimeik ставить гідробокс приблизно у 2× дорожче за кабіну. | G75: 4000
A76: Сантехніка | B76: Сантехніка | C76: Монтаж вентиляційної решітки | D76: шт | E76: 1300 | F76: Абсурдно висока ціна за просту решітку, до того ж вища за «Установка та підключення вентилятора» (425). Ймовірно, ціна зсунулася з іншого рядка. Позиція також не належить до сантехніки.
A77: Сантехніка | B77: Сантехніка | C77: Монтаж панелі з клавішами змиву | D77: шт | E77: 1300 | F77: Завищено: santehprofi бере за встановлення кнопки інсталяції від 500. На ринку унітаз на консолі з кнопкою коштує 1750–1840 разом. | G77: 500
A78: Сантехніка | B78: Сантехніка | C78: Монтаж металевого сифона | D78: шт | E78: 1300 | F78: Вдвічі дорожче за «Установка сифона» (500) і вище за ринковий максимум для сифона, 800 (rabotniki). | G78: 800
A79: Сантехніка | B79: Сантехніка | C79: Монтаж гасника гідроудару (гідрокомпенсатора) | D79: шт | E79: 1300 | F79: Гасник вкручується як фітинг. Тим часом редуктор тиску у нас коштує 500, зворотний клапан 300, кульовий кран 300. Ринкових даних за саму позицію не знайшли; розумна ціна на рівні редуктора (~800).
A80: Сантехніка | B80: Сантехніка | C80: Установка скляних розсувних дверей | D80: шт | E80: 300 | F80: Аномально низько порівняно з «Монтаж скляних шторок на ванну» (2000). rimeik дає за двері на ванну 500 і за двері кабіни 700 (слабке джерело).
A81: Сантехніка | B81: Сантехніка | C81: Монтаж системи від протікання води | D81: шт | E81: 850 | F81: Схоже, ціна занижена: liv-comfort бере за систему «Аквастоп» 2300 за комплект. У нашому комплекті 2 крани з приводом, контролер і датчики, тоді як один кран коштує 250–400. | G81: 2000
A82: Сантехніка | B82: Сантехніка | C82: Запуск системи водопроводу | D82: шт | E82: 1800 | F82: Дорівнює «Запуск системи опалення» (1800). Запуск водопроводу простіший: на ринку опалення запускають за 1400/1743/2500, окремої ринкової позиції для водопроводу немає. Ймовірно, завищено.
A83: Сантехніка | B83: Сантехніка | C83: Монтаж фільтра самопромивного | D83: точка | E83: 400 | F83: Помилкова одиниця: має бути PIECE. Також ціна нижче за ринок 950–1000 (див. checked). | G83: 900
A84: Сантехніка | B84: Сантехніка | C84: Установка фільтра питної води під мийку | D84: точка | E84: 850 | F84: Помилкова одиниця: має бути PIECE. Порівняти можна з осмосом (1500–1600) і фільтром для води Kabanchik (2100), тож 850 для простого 3-ступеневого фільтра прийнятні.
A85: Сантехніка | B85: Сантехніка | C85: Штроблення в газобетоні цеглі (каналізація) | D85: м.п. | E85: 150 | F85: У каталозі чотири різні ціни на штробу в цеглі (300 / 250 / 150 / 150), а каналізаційна штроба дешевша за штробу під воду. Треба вирівняти: вода ≈260, каналізація ≈300. | G85: 300
A86: Сантехніка | B86: Сантехніка | C86: Штроблення в бетоні (каналізація) | D86: м.п. | E86: 200 | F86: Дублікат «Штроблення під трубу 100мм в бетоні» (200), і обидва дешевші за штробу під воду в бетоні (370). На ринку каналізаційна штроба в бетоні коштує 350–500. | G86: 450
A87: Сантехніка | B87: Сантехніка | C87: Прокладання труб на хомутах (каналізація) | D87: м.п. | E87: 220 | F87: Дублікат «Прокладка труб каналізації» (220) з тією самою ціною. Обидві вище за ринок (Ø50 ≈130–160, Ø110 ≈190). | G87: 170
A88: Сантехніка | B88: Сантехніка | C88: Установка УФ знезаражувача води | D88: шт | E88: 2532 | F88: Ціна не кругла (імпорт?). rabotniki по Україні дає 2500/3025/3500. | G88: 3000
A89: Сантехніка | B89: Сантехніка | C89: Установка пелетного котла | D89: шт | E89: 10056 | F89: Ціни не круглі (10056, 5190, 1281, 1203, 825), тобто явно імпортовані з шаблону. 1203 збігається з ціною змішувального вузла в santehprofi.kyiv.ua. Усі вони нижче за ринкові мінімуми (див. checked). | G89: 13000
A90: Сантехніка | B90: Сантехніка | C90: Монтаж колектора водопостачання (гребінки) з кранами на виходах | D90: компл. | E90: 1300 | F90: Майже дублікат «Монтаж колектора гребінки» (Опалення, 1281), ціни різняться без причини. Обидві нижче за ринок ~2000. | G90: 2000
A91: Сантехніка | B91: Сантехніка | C91: Обв'язка радіатора один радіатор 2 точки | D91: точка | E91: 750 | F91: Неоднозначно: у назві «один радіатор 2 точки», а одиниця — точка. Треба явно вказати, за що ціна: за точку чи за радіатор.
A92: Сантехніка | B92: Сантехніка | C92: Установка штанги | D92: шт | E92: 300 | F92: Незрозуміло, що це: душова штанга з лійкою (ринок 580/798/1150, rabotniki; arsel 870) чи штанга для шторки. Якщо душова, 300 занижено.
A93: Сантехніка | B93: Сантехніка | C93: Опломбування лічильника води | D93: шт | E93: 500 | F93: У Києві та Львові пломбує водоканал. Майстер може хіба що організувати процес, тож назву варто змінити («Виклик/організація опломбування»).
A94: Сантехніка | B94: Сантехніка | C94: Прокладка труб в траншеї | D94: м.п. | E94: 50 | F94: Удвічі дешевше за прокладання всередині приміщення (100–180). Прийнятно лише якщо траншею копають окремо, і це треба вказати в описі. santehprofi бере за прокладання водопроводу в землі від 1000/м.п. разом з копанням.
A95: Сантехніка | B95: Сантехніка | C95: Установка люка-ревізії простого | D95: шт | E95: 400 | F95: budver дає за ревізійний люк від 1265. Перевірено лише одним джерелом, тож ціна, можливо, занижена.
A96: Сантехніка | B96: Сантехніка | C96: Монтаж витяжки (без відведення або до існуючого вентканала) | D96: шт | E96: 1500 | F96: Позиції «Монтаж вентиляції» (м.п.), «Витяжка», «Дзеркало», «Дверний доводчик», «Вентилятор» не належать до сантехніки і стоять у категорії «Сантехприлади». Їх краще перенести до загальних або електромонтажних робіт.
A97: Будівельник, демонтаж, метал | B97: Демонтаж | C97: Підйом будматеріалів на поверх | D97: шт | E97: 263 | F97: 263 грн 'за шт' без визначення одиниці. Ринок: 10 грн/мішок/поверх (gruzmen.kiev.ua), 25 грн/поверх/людина (bison-trans.com), +10 грн за поверх (ms-pro.kiev.ua), підйом негабариту 120–130 грн/поверх (rabotniki). Ймовірно мало бути за тонну/поверх або за поверх усього замовлення. Рекомендую одиницю 'мішок до 50 кг за поверх' ≈15 грн, або FLOOR із чітким описом. | G97: 15
A98: Будівельник, демонтаж, метал | B98: Метал | C98: Виготовлення металевого каркасу сходів (за сходинку) | D98: шт | E98: 900 | F98: Не узгоджено з 'Виготовлення сходів на косоурах (за сходинку)' (1350) і BUILDER 'Зварювання каркасу сходів пряма/поворотна сходинка' (1350). Див. checked. | G98: 1350
A99: Будівельник, демонтаж, метал | B99: Будівельник | C99: Виготовлення терас веранд комплекс | D99: м² | E99: 11800 | F99: Аномально високо для 'тільки робота': монтаж терасної дошки 350/538/800 (rabotniki), металокаркас 1800/м² (ecowood), навіть 'Стандартна тераса' ecowood 5300/м² (схоже, з матеріалом). Майже напевно з матеріалами. Робота комплекс ≈ каркас + настил + опори ≈ 2500–3000. | G99: 2800
A100: Будівельник, демонтаж, метал | B100: Будівельник | C100: Навіс легкий / середній / максимальний комплекс (×3), Будівництво гаража комплекс, Хоз блок сарайчик комплекс | D100: м² | E100: 630 | F100: П'ять різних 'комплексів' з однаковою ціною 630 — шаблонна заглушка; 'легкий' = 'максимальний' нелогічно. Ринок для навісу (тільки робота): каркас 850–1800 + покрівля 400–450 ⇒ ~1300–2200/м² (rating-remont, ecowood, rabotniki). Розставити градацію, напр. 1300/1700/2200; гараж/хозблок — окремо оцінити.
...

Sheet Нові позиції
A1: Група | B1: Фах | C1: Назва | D1: Од. | E1: Ринковий діапазон | F1: Джерела | G1: Додати? | H1: Ціна для каталогу, ₴
A2: Плитка і підлоги | B2: Підлоги | C2: Монтаж електричної теплої підлоги (мат/кабель) | D2: м² | E2: 250–350 грн/м² (remonthub: від 250; Львів 280–350) | F2: https://www.remonthub.org/prices.php https://rating-remont-kvartir.com.ua/ua/rozcinki-na-roboti-z-pidlogami-lviv/
A3: Плитка і підлоги | B3: Підлоги | C3: Підключення теплої підлоги до терморегулятора | D3: шт | E3: ~350 грн/шт | F3: https://www.remonthub.org/prices.php
A4: Плитка і підлоги | B4: Плитка | C4: Облицювання кухонного фартуха плиткою | D4: м² | E4: 700–1050 грн/м² (PK: ×1.1 від базової) | F4: https://liv-comfort.kyiv.ua/price-remont/index.html https://remmo.lviv.ua/plytochni-roboty-lviv/ https://plitochnik.kiev.ua/ua/%D0%B2%D0%B0%D1%80%D1%82%D1%96%D1%81%D1%82%D1%8C-%D1%80%D0%BE%D0%B1%D1%96%D1%82-%D0%BF%D0%BB%D0%B8%D1%82%D0%BE%D1%87%D0%BD%D0%B8%D0%BA%D0%B0.html
A5: Плитка і підлоги | B5: Плитка | C5: Облицювання відкосів/укосів плиткою (за м.п.) | D5: м.п. | E5: 500–1300 грн/м.п. (rabotniki сер. 834; remonthub 500; remmo 650; budver від 528) | F5: https://www.rabotniki.ua/uk/plitochnye-raboty https://www.remonthub.org/prices.php https://remmo.lviv.ua/plytochni-roboty-lviv/ https://budver.com/masters/plitochni-roboti
A6: Плитка і підлоги | B6: Підлоги | C6: Демонтаж ламінату | D6: м² | E6: 130–160 грн/м² | F6: https://rbk-alba.com/ua/price https://kabanchik.ua/ua/kyiv/category/ukladannia-laminatu
A7: Плитка і підлоги | B7: Підлоги | C7: Демонтаж паркету / дерев'яної підлоги | D7: м² | E7: 100–200 грн/м² | F7: https://rbk-alba.com/ua/price https://rating-remont-kvartir.com.ua/ua/rozcinki-na-roboti-z-pidlogami-lviv/
A8: Плитка і підлоги | B8: Підлоги | C8: Демонтаж ПВХ-плитки / кварцвінілу | D8: м² | E8: ~250 грн/м² | F8: https://rbk-alba.com/ua/price
A9: Плитка і підлоги | B9: Плитка | C9: Демонтаж керамічного плінтуса | D9: м.п. | E9: ~260 грн/м.п. | F9: https://rbk-alba.com/ua/price
A10: Плитка і підлоги | B10: Підлоги | C10: Встановлення маяків для стяжки | D10: м² | E10: 85–130 грн/м² (rabotniki 104/122/130; arsel 85) | F10: https://www.rabotniki.ua/uk/chernovye-raboty-po-polu/kiev https://bud.arsel.com.ua/tsiny-na-budivelni-roboty/
A11: Плитка і підлоги | B11: Підлоги | C11: Стяжка з пінополістиролбетону | D11: м² | E11: 305–500 грн/м² (rabotniki 390/448/500; arsel 305) | F11: https://www.rabotniki.ua/uk/chernovye-raboty-po-polu/kiev https://bud.arsel.com.ua/tsiny-na-budivelni-roboty/
A12: Плитка і підлоги | B12: Підлоги | C12: Укладання кварцвінілу ялинкою | D12: м² | E12: ~700 грн/м² | F12: https://parket-doska.com.ua/ukladannya-parketu-iz-zavodskoyu-obrobkoyu-malyunok-francuzka-rizka-ugorska-yalinka-na-styazhku/
A13: Плитка і підлоги | B13: Підлоги | C13: Радіусна (фігурна) підрізка ламінату | D13: м.п. | E13: ~150 грн/м.п. | F13: https://www.remonthub.org/prices.php
... A64: Будівельник, демонтаж, метал | B64: Метал | C64: Зварювальний шов (за м.п.: MMA / напівавтомат / аргон) | D64: м.п. | E64: від 100 / від 120 / від 200 (rating-remont); 258–541 за м.п. при кромці 4–6 мм (duga.in.ua); труби d21–d42 250–400 (kabanchik) | F64: https://rating-remont-kvartir.com.ua/ua/rozcinki-na-zvarjuvalni-roboti/ https://duga.in.ua/ua/prajs2.html https://kabanchik.ua/ua/kyiv/tag/posluhy-zvariuvalnyka

Sheet Джерела
A1: Джерело | B1: Що там є | C1: Актуальність | D1: Якість | E1: Нове (не було у попередніх рев'ю) | F1: Групи, де використано
A2: rabotniki.ua | B2: Мін/сер/макс за десятками позицій, окремо Київ і Львів: кладка, фасад, покрівля, бетон, фундамент, тротуарна плитка, монтаж ФБС/армопояс, демонтаж (стіни, підлога, вікна/двері, отвори), вивіз/винос сміття, вантажники, паркани, ворота/хвіртки, сходи, навіси, ковка, демонтаж/зварювання металоконструкцій | C2: 2026-10 | D2: добре | E2: ні | F2: Плитка і підлоги, Малярка і гіпсокартон, Електрика, Сантехніка, Будівельник, демонтаж, метал
A3: bud.arsel.com.ua | B3: Київ: демонтаж (перегородки, стяжка, плитка, двері, вікна, отвори), фасад/вентфасад 'від', покрівля 'від' | C3: 2026-01 | D3: добре | E3: так | F3: Плитка і підлоги, Малярка і гіпсокартон, Електрика, Сантехніка, Будівельник, демонтаж, метал
A4: rbk-alba.com | B4: Великий київський прайс (~250 позицій демонтажу + кам'яні та бетонні роботи); дата оновлення 19.10.2026; демонтаж помітно вище бюджетного сегменту | C4: 2026-10 | D4: добре | E4: так | F4: Плитка і підлоги, Малярка і гіпсокартон, Електрика, Сантехніка, Будівельник, демонтаж, метал
A5: plitochnik.kiev.ua | B5: Детальний прайс плиткової бригади з Києва (формати, 45°, отвори, затирки, гідроізоляція, вироби), окрема сторінка для широкоформатного керамограніту. Структура дуже схожа на наш каталог | C5: 2026 | D5: добре | E5: так | F5: Плитка і підлоги
A6: amperage.com.ua | B6: Прайс електромонтажної компанії зі Львова: ~70 позицій (щит за модулями, автомати за полюсами, ПЗВ 2/4п, перемикачі аварійного живлення, трек, LED, точкові з отворами). | C6: 2026 (стор. змінено 05.2026) | D6: добре | E6: так | F6: Електрика
A7: altek.kiev.ua | B7: Прайс електрика з Києва 2026: коробки за матеріалами, штроба з закладенням, плита/духовка, бойлер, реле, інвертор, генератор, виїзд, години, надбавки +30%. | C7: 2026 | D7: добре | E7: так | F7: Електрика
A8: pilo-material.kiev.ua | B8: Київський прайс покрівельних робіт, явно 'тільки робота' (металочерепиця, профнастил, бітумна, крокви, обрешітка, утеплення, водостоки) | C8: 2026-10 | D8: добре | E8: так | F8: Будівельник, демонтаж, метал
A9: pl2t.com | B9: Київ: детальний прайс укладання тротуарної плитки, бордюрів, гарцовки, основи, люків/піскоприймачів | C9: 2026-07 | D9: добре | E9: так | F9: Будівельник, демонтаж, метал
A10: budver.com | B10: Маркетплейс майстрів: ціни 'від' і мін/сер/макс (затирка, епоксидка, гідроізоляція, 45°, кабанчик). Схоже на шаблон (та сама кількість майстрів 1119, макс = 2,5–3×мін) | C10: 2026 | D10: нормально | E10: ні | F10: Плитка і підлоги, Малярка і гіпсокартон, Електрика, Сантехніка, Будівельник, демонтаж, метал
A11: kabanchik.ua | B11: Категорія «Електрик» Київ: блоки «від» (стабілізатор, лічильник, щит, домофон, люстри) і фіксований блок «Вартість послуг»; також «Інші послуги електрика» і «Установка духової шафи». Ціни «від» місцями і завищені, і занижені, тож бралися обережно. | C11: 2026-10 | D11: нормально | E11: ні | F11: Плитка і підлоги, Малярка і гіпсокартон, Електрика, Сантехніка, Будівельник, демонтаж, метал
A12: remonthub.org | B12: Київський прайс-лист 2026: плитка, затирки, гідроізоляція, стяжка, ламінат, тепла підлога | C12: 2026 | D12: нормально | E12: так | F12: Плитка і підлоги, Малярка і гіпсокартон, Електрика, Сантехніка, Будівельник, демонтаж, метал
... A39: ecowood.com.ua | B39: Тераси: металокаркас із профтруби 1800 грн/м², 'Стандартна тераса' 5300 грн/м² (неясно чи з матеріалом) | C39: н/д | D39: слабко | E39: так | F39: Будівельник, демонтаж, метал
